simple_pim/simple_pim/model/cfu/sim/EqualTest/not_fix_test/src/cfu.v
module cfu#(
    parameter PIM_ADDR_BEGIN = 'h000,
    parameter DWIDTH = 32,   // DATA WIDTH
    parameter AWIDTH = 10,    // ADDRESS WIDTH
    parameter PWIDTH = 32,   // PIM WIDTH
    parameter PDEPTH = (1 << AWIDTH) // PIM DEPTH
)(
    input [PWIDTH-1:0] cmd_payload_inputs_0,    // d
    input [PWIDTH-1:0] cmd_payload_inputs_1,    // addr
    input [AWIDTH-1:0] cmd_payload_function_id,
    input clk,
    input reset,
    input cmd_valid,
    output cmd_ready,
    output rsp_valid,
    input rsp_ready,
    output rsp_payload_response_ok,
    output [DWIDTH-1:0] rsp_payload_outputs_0
);

    reg [PWIDTH-1:0] mem [PIM_ADDR_BEGIN:PIM_ADDR_BEGIN+PDEPTH-1];
    reg [DWIDTH-1:0] adc_out [0:PWIDTH-1];
    reg [4:0] shift_cnt;
    reg [DWIDTH-1:0] acc_result [0:PWIDTH-1];
    reg [DWIDTH-1:0] sum_acc_result;
    reg [DWIDTH-1:0] mac_out_reg;
    reg [PWIDTH-1:0] q_reg;
    reg [DWIDTH-1:0] out;

    wire p_en, w_en;
    assign p_en = cmd_payload_function_id[1];
    assign w_en = cmd_payload_function_id[0];

    wire [7:0] mem_addr = cmd_payload_inputs_1[7:0];

    reg ready;
    reg valid;
    assign cmd_ready = ready;
    assign rsp_valid = valid;

    assign rsp_payload_response_ok = 1'b1;

    integer i, j;

    initial begin 
        for (i = PIM_ADDR_BEGIN; i < PIM_ADDR_BEGIN + PDEPTH; i = i+1) begin
            mem[i] = 0;
        end
    end

    reg [DWIDTH-1:0] temp_sum_acc_result;

    reg [PDEPTH-1:0] rwl;
    reg [31:0] count;

    always @(posedge clk or posedge reset) begin
        if (reset) begin
            rwl <= 0;
            count <= 0;
        end else begin
            if (count != 0) rwl <= rwl;
            else begin
                rwl <= $urandom;
            end
        end
    end

    always @(posedge clk or posedge reset) begin
        if (reset) begin 
            shift_cnt <= 0;
            for (i = 0; i < PWIDTH; i = i+1) begin
                acc_result[i] <= 0;
                adc_out[i] <= 0;
            end
            sum_acc_result <= 0;
            q_reg <= 0;
            mac_out_reg <= 0;
            count <= 0;

            ready <= 1'b0;
            valid <= 1'b0;
        end else begin
            if (cmd_valid) begin
                ready <= 1'b1;
                if (!p_en) begin // Memory operation
                    count <= 0;
                    // $display("rwl :  %h", rwl);
                    if (w_en) begin
                        mem[mem_addr] <= cmd_payload_inputs_0;
                        $display("p_en = %0d, w_en = %0d", p_en, w_en);
                        // $display("Write: mem[%d] <= %h", mem_addr, cmd_payload_inputs_0);
                        // $display("=====================================================");
                    end else begin
                        q_reg <= mem[mem_addr];
                        $display("p_en = %0d, w_en = %0d", p_en, w_en);
                        // $display("Read: mem[%d] -> %h", mem_addr, mem[mem_addr]);
                        // $display("=====================================================");
                    end
                    shift_cnt <= 0;
                    for (i = 0; i < PWIDTH; i = i+1) begin
                        acc_result[i] <= 0;
                    end
                end 
                else begin // MAC operation
                    // 
                    $display("p_en = %0d, w_en = %0d", p_en, w_en);
                    // $display("rwl : %h", rwl);
                    count <= count + 1;

                    // for (j = 0; j < PDEPTH; j = j + 1) begin
                    //     $display("mem[%0d]: %h, rwl[%0d]: %b", j, mem[j], j, rwl[j]);
                    // end

                    // for (i = 0; i < PWIDTH; i = i+1) begin
                    //     $display("adc_out[%0d]: %h", i, adc_out[i]);
                    // end
                    
                    for (i = 0; i < PWIDTH; i = i+1) begin
                        // $display("Before Accumulate: acc_result[%0d] = %h", i, acc_result[i]);
                        acc_result[i] <= (shift_cnt == 0) ? adc_out[i] : acc_result[i] + (adc_out[i] << shift_cnt);
                        // if (shift_cnt == 0) $display("After  Accumulate: shift_cnt : %0d, acc_result[%0d] = %h", shift_cnt, i, adc_out[i]);
                        // else $display("After  Accumulate: shift_cnt : %0d, acc_result[%0d] = %h <= %h + %h << %h", shift_cnt, i, acc_result[i] + (adc_out[i] << shift_cnt), acc_result[i], adc_out[i], shift_cnt);                       
                    end
                    // $display("before shift_cnt: %0d", shift_cnt);
                    shift_cnt <= shift_cnt + 1;
                    // $display("After  shift_cnt: %0d", shift_cnt + 1);

                    temp_sum_acc_result = 0;
                    
                    for (i = 0; i < PWIDTH; i = i+1) begin
                        temp_sum_acc_result = temp_sum_acc_result + acc_result[i];
                        sum_acc_result <= temp_sum_acc_result;
                    end
                    // $display("Sum Accumulate Result: %h", sum_acc_result);
                    mac_out_reg <= sum_acc_result;
                    $display("MAC Result: %h", mac_out_reg); // Print MAC result
                end
                valid <= 1'b1;
            end 
            else begin
                ready <= 1'b0;
                valid <= 1'b0;                
            end
        end
    end

    always @(*) begin
        for (i = 0; i < PWIDTH; i = i+1) begin  
            for (j = 0; j < PDEPTH; j = j+1) begin
                if (shift_cnt == 0)     adc_out[i] = 0;
                else                    adc_out[i] = adc_out[i] + ({PWIDTH{mem[PIM_ADDR_BEGIN + j][i]}} & {PWIDTH{rwl[j]}});
                // else                    adc_out[i] = adc_out[i] + ({32{mem[PIM_ADDR_BEGIN + j][i]}} & {32{rwl[j]}});

            end
        end
    end

    always @(posedge clk or posedge reset) begin
        if(reset) begin
            out <= 32'd0;
        end else begin
            if (p_en) begin
                out <= mac_out_reg;
            end else begin
                if (w_en) begin
                    out <= cmd_payload_inputs_0; 
                    // out <= mem[mem_addr]; 
                end else begin 
                    out <= q_reg;
                end
            end
        end
    end

    assign rsp_payload_outputs_0 = out;

endmodule

simple_pim/model/cfu/sim/EqualTest/fix_test/src/testbench.v
module tb_cfu;

    // Parameters
    parameter PIM_ADDR_BEGIN = 'h000;
    parameter DWIDTH = 32;
    parameter AWIDTH = 10;
    parameter PWIDTH = 32;
    parameter PDEPTH = (1 << AWIDTH);

    // Testbench signals
    reg [PWIDTH-1:0] cmd_payload_inputs_0;
    reg [PWIDTH-1:0] cmd_payload_inputs_1;
    reg [AWIDTH-1:0] cmd_payload_function_id;
    reg clk;
    reg reset;
    reg cmd_valid;
    wire cmd_ready;
    wire rsp_valid;
    reg rsp_ready;
    wire rsp_payload_response_ok;
    wire [DWIDTH-1:0] rsp_payload_outputs_0;

    // Instantiate the CFU module
    cfu #(
        .PIM_ADDR_BEGIN(PIM_ADDR_BEGIN),
        .DWIDTH(DWIDTH),
        .AWIDTH(AWIDTH),
        .PWIDTH(PWIDTH),
        .PDEPTH(PDEPTH)
    ) uut (
        .cmd_payload_inputs_0(cmd_payload_inputs_0),
        .cmd_payload_inputs_1(cmd_payload_inputs_1),
        .cmd_payload_function_id(cmd_payload_function_id),
        .clk(clk),
        .reset(reset),
        .cmd_valid(cmd_valid),
        .cmd_ready(cmd_ready),
        .rsp_valid(rsp_valid),
        .rsp_ready(rsp_ready),
        .rsp_payload_response_ok(rsp_payload_response_ok),
        .rsp_payload_outputs_0(rsp_payload_outputs_0)
    );

    // Clock generation
    always #5 clk = ~clk;

    integer i, j, k, s, mac_index;
    reg [DWIDTH-1:0] write_data [0:255];  // Store the data to write, adjusted size to 256
    reg [DWIDTH-1:0] expected_data [0:255];  // To keep track of what should be written, adjusted size to 256
    reg [DWIDTH-1:0] read_data [0:255];  // To store the read values, adjusted size to 256
    reg [255:0] write_occurred;  // Track if a write occurred at an address, adjusted size to 256
    reg [DWIDTH-1:0] mac_out_array [0:255];
    reg [DWIDTH-1:0] expected_mac_out_array [0:255];
    reg [7:0] addr;  // Address is 8-bit to match address space (0-255)
    reg [9:0] not_match;
    reg [DWIDTH-1:0] expected_mac_out;
    reg [DWIDTH-1:0] mac_out_count;

    reg [DWIDTH-1:0] adc_out [0:PWIDTH-1];
    reg [DWIDTH-1:0] acc_result [0:PWIDTH-1];
    reg [DWIDTH-1:0] mem [0:255];
    reg [31:0] rwl;
    reg [4:0] shift_cnt;
    // reg [4:0] shift_cnt_reg;
    reg test1, test2, test3;
    reg [DWIDTH-1:0] temp_sum_acc_result;
    reg [DWIDTH-1:0] sum_acc_result;

    initial begin
        // Initialize signals
        clk = 0;
        reset = 1;
        cmd_valid = 0;
        rsp_ready = 0;
        cmd_payload_inputs_0 = 0;
        cmd_payload_inputs_1 = 0;
        cmd_payload_function_id = 0;
        not_match = 0;  // Initialize not_match counter
        write_occurred = 0; // Initialize write tracking
        mac_out_count = 0;
        mac_index = 0;  // Initialize mac_out index
        shift_cnt = 0;
        // shift_cnt_reg = 0;
        expected_mac_out = 0;
        sum_acc_result = 0;

        // TEST
        test1 = 0;
        test2 = 1;
        test3 = 1;

        // Apply reset
        #10;
        reset = 0;

        // Initialize data to write, expected data, and read_data
        for (i = 0; i < 256; i = i + 1) begin
            write_data[i] = 32'h0;  // Initialize write data to zero to avoid 'xxxxxxxx'
            expected_data[i] = 32'h0;  // Initialize expected data to zero
            read_data[i] = 32'h0;      // Initialize read value to zero
        end

        $display("=============== TEST START ===============");
        $display("==========================================");

        // Test random write operations for 30 addresses
        // Perform 100 random write operations
        for (s = 0; s < 50; s = s + 1) begin
            $display("TEST [%d]", s);
            addr = $random % 256;  // Choose random address for Write operation
            cmd_payload_function_id = $random % 4;

            // Generate random write data (non-zero)
            write_data[addr] = $random;
            if (write_data[addr] == 0) write_data[addr] = $random | 32'h1; // Ensure non-zero data

            // Handle write operation
            if (cmd_payload_function_id[1:0] == 2'b01) begin
                // Write operation
                cmd_valid = 1;
                cmd_payload_inputs_0 = write_data[addr];  // Data to write
                cmd_payload_inputs_1 = addr;              // Address to write to
                #10;
                cmd_valid = 0;
                #10;

                // Store the written data to expected data for later verification
                expected_data[addr] = write_data[addr];
                write_occurred[addr] = 1; // Mark that a write occurred to this address

                // Display write operation in real-time
                $display("write [%0d] <- %h", addr, write_data[addr]);

                shift_cnt <= 0;
                for (i = 0; i < PWIDTH; i = i+1) begin
                    acc_result[i] <= 0;
                    adc_out[i] <= 0;
                end
            end
            // Handle read operation
            else if (cmd_payload_function_id[1:0] == 2'b00) begin
                cmd_valid = 1;
                cmd_payload_inputs_1 = addr;      // Address to read from
                #10;
                cmd_valid = 0;
                #10;

                // Store the read data
                read_data[addr] = rsp_payload_outputs_0;

                shift_cnt <= 0;
                for (i = 0; i < PWIDTH; i = i+1) begin
                    acc_result[i] <= 0;
                end

                // Display read operation in real-time
                $display("read [%0d] -> %h", addr, rsp_payload_outputs_0);
            end
            // Handle MAC operation (example, display MAC result)
            else begin
                // MAC operation
                cmd_valid = 1;
                cmd_payload_inputs_1 = addr;
                #10;
                cmd_valid = 0;
                #10;

                for (j = 0; j < PWIDTH; j = j + 1) begin
                    if (shift_cnt == 0) adc_out[j] = 0;
                    else begin
                        for (k = 0; k < PDEPTH; k = k + 1) begin
                            adc_out[j] = adc_out[j] + ({32{uut.mem[k][j]}} & {32{uut.rwl[k]}});
                        end
                    end
                end

                for (i = 0; i < PWIDTH; i = i+1) begin
                    acc_result[i] <= (shift_cnt == 0) ? adc_out[i] : acc_result[i] + (adc_out[i] << shift_cnt);
                end

                shift_cnt <= shift_cnt + 1;

                temp_sum_acc_result = 0;
                for (j = 0; j < PWIDTH; j = j + 1) begin
                    temp_sum_acc_result = temp_sum_acc_result + acc_result[j];
                end
                sum_acc_result = temp_sum_acc_result;
                expected_mac_out <= sum_acc_result;
                $display("MAC Result: %h", expected_mac_out); // Print MAC result

                mac_out_array[mac_index] = rsp_payload_outputs_0;
                expected_mac_out_array[mac_index] = expected_mac_out;
                mac_index = mac_index + 1;

                if (mac_index > 1000) begin
                    $display("\nXXX Exceed XXX");
                    $finish;
                end
            end

        end

        $display("\n============= TEST  Evaluate =============");

        // ============================================================================================
        $display("\nTEST 1: Read All");
        $display("address         write                 read");

        // Display the final table of addresses, write and read values
        for (i = 0; i < 256; i = i + 1) begin
            if (write_occurred[i]) begin
                $display("%03d           %h       ->     %h", i, expected_data[i], read_data[i]);
            end 
            else begin
                $display("%03d           00000000              00000000", i);
            end
        end

        if (test1 == 0)         $display("✓ TEST 1 Sucess !");
        else                    $display("x TEST 1 Fail !");

        // ============================================================================================
        $display("\nTEST 2: Read what you wrote");
        $display("address         write                 read");

        for (i = 0; i < 256; i = i + 1) begin
            if (write_occurred[i]) begin
                if (read_data[i] == expected_data[i]) begin
                    $display("%03d           %h       ->     %h", i, expected_data[i], read_data[i]);
                end 
                else if (read_data[i] == 0) begin
                    $display("%03d           %h       ->     %h", i, expected_data[i], read_data[i]);
                end
                else begin
                    $display("%03d           %h              %h  (Mismatch!)", i, expected_data[i], read_data[i]);
                    not_match = not_match + 1;
                    test2 = 0;
                end
            end
        end

        if (test2 == 1)     $display("✓ TEST 2 Sucess !");
        else                $display("x TEST 2 Fail !");
        
        // ============================================================================================
        $display("\nTEST 3: Calculate macout");
        for (i = 0; i < mac_index; i = i + 1) begin
            if (mac_out_array[i] == expected_mac_out_array[i]) begin
                $display("MAC operation %02d: Expected = %h, Actual = %h  (Pass!)", i, expected_mac_out_array[i], mac_out_array[i]);
            end else begin
                $display("MAC operation %02d: Expected = %h, Actual = %h  (Mismatch!)", i, expected_mac_out_array[i], mac_out_array[i]);
                not_match = not_match + 1;
                test3 = 0;
            end
        end

        if (test3 == 1)     $display("✓ TEST 3 Sucess !");
        else                $display("x TEST 3 Fail !");

        // ============================================================================================
        
        if ((test1 == 0) && (test2 == 1) && (test3 == 1)) begin
            $display("\nAll Pass!");
        end 
        else begin
            $display("\nTest completed with %0d mismatches.", not_match);
        end

        $display("==========================================");
        // Finish simulation
        $finish;
    end

    initial begin
        $dumpvars(0, uut);
        $dumpfile("cfu.vcd");
    end

endmodule

simple_pim/model/cfu/sim/EqualTest/not_fix_test/dump.vcd
$date
	Fri Mar 21 14:09:18 2025
$end
$version
	Icarus Verilog
$end
$timescale
	1ps
$end
$scope module tb_cfu $end
$scope module uut $end
$var wire 1 ! clk $end
$var wire 10 " cmd_payload_function_id [9:0] $end
$var wire 32 # cmd_payload_inputs_0 [31:0] $end
$var wire 32 $ cmd_payload_inputs_1 [31:0] $end
$var wire 1 % cmd_ready $end
$var wire 1 & cmd_valid $end
$var wire 1 ' reset $end
$var wire 32 ( rsp_payload_outputs_0 [31:0] $end
$var wire 1 ) rsp_payload_response_ok $end
$var wire 1 * rsp_ready $end
$var wire 1 + rsp_valid $end
$var wire 1 , w_en $end
$var wire 1 - p_en $end
$var wire 8 . mem_addr [7:0] $end
$var reg 32 / count [31:0] $end
$var reg 32 0 mac_out_reg [31:0] $end
$var reg 32 1 out [31:0] $end
$var reg 32 2 q_reg [31:0] $end
$var reg 1 3 ready $end
$var reg 1024 4 rwl [1023:0] $end
$var reg 5 5 shift_cnt [4:0] $end
$var reg 32 6 sum_acc_result [31:0] $end
$var reg 32 7 temp_sum_acc_result [31:0] $end
$var reg 1 8 valid $end
$var integer 32 9 i [31:0] $end
$var integer 32 : j [31:0] $end
$upscope $end
$upscope $end
$enddefinitions $end
#0
$dumpvars
b10000000000 :
b100000 9
08
bx 7
b0 6
b0 5
b0 4
03
b0 2
b0 1
b0 0
b0 /
b0 .
0-
0,
0+
0*
1)
b0 (
1'
0&
0%
b0 $
b0 #
b0 "
0!
$end
#5000
b100000 9
1!
#10000
b100100 .
1,
0!
b100100 $
b10000100100001001101011000001001 #
1&
b1111111101 "
0'
#15000
b10000000000 :
b10010010000101010011010100100100 4
1+
18
1%
13
b10000100100001001101011000001001 (
b10000100100001001101011000001001 1
b100000 9
1!
#20000
0!
0&
#25000
b10000000000 :
b100000 9
0+
08
0%
03
b1000000100010010101111010000001 4
1!
#30000
b1100011 .
0!
b1100011 $
b1000110110111111001100110001101 #
1&
b1 "
#35000
b10000000000 :
b100100001001101011000001001 4
1+
18
1%
13
b1000110110111111001100110001101 (
b1000110110111111001100110001101 1
b100000 9
1!
#40000
0!
0&
#45000
b10000000000 :
b100000 9
0+
08
0%
03
b110001111100000101011001100011 4
1!
#50000
b1100101 .
1-
0,
0!
b1100101 $
1&
b1111111110 "
#55000
b10000000000 :
b10000110101110010111101100001101 4
1+
18
b1 5
b1 /
1%
13
b0 (
b0 1
b0 7
b100000 9
1!
#60000
0!
0&
#65000
0+
08
0%
03
1!
#70000
b1101 .
0!
b1101 $
1&
b10 "
#75000
b10000000000 :
1+
18
b10 5
b10 /
1%
13
b100000 9
1!
#80000
0!
0&
#85000
0+
08
0%
03
1!
#90000
b11101101 .
0-
0!
b11101101 $
1&
b0 "
#95000
b10000000000 :
1+
18
b0 5
b0 /
1%
13
b100000 9
1!
#100000
0!
0&
#105000
b10000000000 :
b100000 9
0+
08
0%
03
b11000110110111111001100110001101 4
1!
#110000
b11000110 .
1,
0!
b11000110 $
b11010101000100111101001010101010 #
1&
b1111111101 "
#115000
b10000000000 :
b110010110000101000010001100101 4
1+
18
1%
13
b11010101000100111101001010101010 (
b11010101000100111101001010101010 1
b100000 9
1!
#120000
0!
0&
#125000
b10000000000 :
b100000 9
0+
08
0%
03
b1001001101110101001000010010 4
1!
#130000
b11100101 .
1-
0!
b11100101 $
1&
b1111111111 "
#135000
b10000000000 :
b10000000111100111110001100000001 4
1+
18
b1 5
b1 /
1%
13
b0 (
b0 1
b100000 9
1!
#140000
0!
0&
#145000
0+
08
0%
03
1!
#150000
b10001111 .
0,
0!
b10001111 $
1&
b10 "
#155000
b10000000000 :
1+
18
b10 5
b10 /
1%
13
b100000 9
1!
#160000
0!
0&
#165000
0+
08
0%
03
1!
#170000
b11101000 .
0-
1,
0!
b11101000 $
b101110010110000100100101011100 #
1&
b1111111101 "
#175000
b10000000000 :
1+
18
b0 5
b0 /
1%
13
b101110010110000100100101011100 (
b101110010110000100100101011100 1
b100000 9
1!
#180000
0!
0&
#185000
b10000000000 :
b100000 9
0+
08
0%
03
b10000110110101111100110100001101 4
1!
#190000
b10111101 .
0!
b10111101 $
b10110010101001110010011001100101 #
1&
#195000
b10000000000 :
b10111011001000111111000101110110 4
1+
18
1%
13
b10110010101001110010011001100101 (
b10110010101001110010011001100101 1
b100000 9
1!
#200000
0!
0&
#205000
b10000000000 :
b100000 9
0+
08
0%
03
b10011110100011011100110100111101 4
1!
#210000
b1100011 .
1-
0,
0!
b1100011 $
1&
b10 "
#215000
b10000000000 :
b11110110110101000101011111101101 4
1+
18
b1 5
b1 /
1%
13
b0 (
b0 1
b100000 9
1!
#220000
0!
0&
#225000
0+
08
0%
03
1!
#230000
b100000 .
0!
b100000 $
1&
#235000
b10000000000 :
1+
18
b10 5
b10 /
1%
13
b100000 9
1!
#240000
0!
0&
#245000
0+
08
0%
03
1!
#250000
b10010110 .
1,
0!
b10010110 $
1&
b1111111111 "
#255000
b10000000000 :
1+
18
b11 5
b11 /
1%
13
b100000 9
1!
#260000
0!
0&
#265000
0+
08
0%
03
1!
#270000
b1010011 .
0!
b1010011 $
1&
b11 "
#275000
b10000000000 :
1+
18
b100 5
b100 /
1%
13
b100000 9
1!
#280000
0!
0&
#285000
0+
08
0%
03
1!
#290000
b10 .
0,
0!
b10 $
1&
b1111111110 "
#295000
b10000000000 :
1+
18
b101 5
b101 /
1%
13
b100000 9
1!
#300000
0!
0&
#305000
0+
08
0%
03
1!
#310000
b11001111 .
1,
0!
b11001111 $
1&
b11 "
#315000
b10000000000 :
1+
18
b110 5
b110 /
1%
13
b100000 9
1!
#320000
0!
0&
#325000
0+
08
0%
03
1!
#330000
b11001010 .
0-
0,
0!
b11001010 $
1&
b0 "
#335000
b10000000000 :
1+
18
b0 5
b0 /
1%
13
b100000 9
1!
#340000
0!
0&
#345000
b10000000000 :
b100000 9
0+
08
0%
03
b11000110001011011111011110001100 4
1!
#350000
b10001010 .
1,
0!
b10001010 $
b11101100010010110011010011011000 #
1&
b1 "
#355000
b10000000000 :
b11111100111111011110100111111001 4
1+
18
1%
13
b11101100010010110011010011011000 (
b11101100010010110011010011011000 1
b100000 9
1!
#360000
0!
0&
#365000
b10000000000 :
b100000 9
0+
08
0%
03
b1100011001101110010010011000110 4
1!
#370000
b1111000 .
0!
b1111000 $
b1110101110001010000110111101011 #
1&
b1111111101 "
#375000
b10000000000 :
b1100010111101111000010011000101 4
1+
18
1%
13
b1110101110001010000110111101011 (
b1110101110001010000110111101011 1
b100000 9
1!
#380000
0!
0&
#385000
b10000000000 :
b100000 9
0+
08
0%
03
b1010101000100111101001010101010 4
1!
#390000
b10110110 .
1-
0,
0!
b10110110 $
1&
b10 "
#395000
b10000000000 :
b11110010101011111111011111100101 4
1+
18
b1 5
b1 /
1%
13
b0 (
b0 1
b100000 9
1!
#400000
0!
0&
#405000
0+
08
0%
03
1!
#410000
b10111100 .
0!
b10111100 $
1&
#415000
b10000000000 :
1+
18
b10 5
b10 /
1%
13
b100000 9
1!
#420000
0!
0&
#425000
0+
08
0%
03
1!
#430000
b1110001 .
0-
1,
0!
b1110001 $
b100111111100100101010101001111 #
1&
b1 "
#435000
b10000000000 :
1+
18
b0 5
b0 /
1%
13
b100111111100100101010101001111 (
b100111111100100101010101001111 1
b100000 9
1!
#440000
0!
0&
#445000
b10000000000 :
b100000 9
0+
08
0%
03
b111011110100100111001001110111 4
1!
#450000
b111011 .
1-
0,
0!
b111011 $
1&
b10 "
#455000
b10000000000 :
b1001001100101101011000010010 4
1+
18
b1 5
b1 /
1%
13
b0 (
b0 1
b100000 9
1!
#460000
0!
0&
#465000
0+
08
0%
03
1!
#470000
b10101 .
0-
1,
0!
b10101 $
b1101100100111000100101111011001 #
1&
b1 "
#475000
b10000000000 :
1+
18
b0 5
b0 /
1%
13
b1101100100111000100101111011001 (
b1101100100111000100101111011001 1
b100000 9
1!
#480000
0!
0&
#485000
b10000000000 :
b100000 9
0+
08
0%
03
b11000111111011001101101110001111 4
1!
#490000
b1100010 .
0,
0!
b1100010 $
1&
b0 "
#495000
b10000000000 :
b11111001001100000110100111110010 4
1+
18
1%
13
b0 (
b0 1
b100000 9
1!
#500000
0!
0&
#505000
b10000000000 :
b100000 9
0+
08
0%
03
b1100111011101101001011011001110 4
1!
#510000
b10001111 .
0!
b10001111 $
1&
#515000
b10000000000 :
b1110100000000000111101011101000 4
1+
18
1%
13
b100000 9
1!
#520000
0!
0&
#525000
b10000000000 :
b100000 9
0+
08
0%
03
b1100010110010100100111011000101 4
1!
#530000
b10011111 .
0!
b10011111 $
1&
#535000
b10000000000 :
b10101110010110000100100101011100 4
1+
18
1%
13
b100000 9
1!
#540000
0!
0&
#545000
b10000000000 :
b100000 9
0+
08
0%
03
b1011110100011100010100010111101 4
1!
#550000
b10001001 .
1,
0!
b10001001 $
b11101000001000110011111011010000 #
1&
b1111111101 "
#555000
b10000000000 :
b10110101010110101100000101101 4
1+
18
1%
13
b11101000001000110011111011010000 (
b11101000001000110011111011010000 1
b100000 9
1!
#560000
0!
0&
#565000
b10000000000 :
b100000 9
0+
08
0%
03
b110010101001110010011001100101 4
1!
#570000
b11010111 .
0!
b11010111 $
b1001011001000010010111110010110 #
1&
#575000
b10000000000 :
b110001111011110110001001100011 4
1+
18
1%
13
b1001011001000010010111110010110 (
b1001011001000010010111110010110 1
b100000 9
1!
#580000
0!
0&
#585000
b10000000000 :
b100000 9
0+
08
0%
03
b10000101011100111000011100001010 4
1!
#590000
b1100 .
1-
0,
0!
b1100 $
1&
b1111111110 "
#595000
b10000000000 :
b1000000001110110010001010000000 4
1+
18
b1 5
b1 /
1%
13
b0 (
b0 1
b100000 9
1!
#600000
0!
0&
#605000
0+
08
0%
03
1!
#610000
b1110111 .
0-
1,
0!
b1110111 $
b1001000011001101101100010010 #
1&
b1 "
#615000
b10000000000 :
1+
18
b0 5
b0 /
1%
13
b1001000011001101101100010010 (
b1001000011001101101100010010 1
b100000 9
1!
#620000
0!
0&
#625000
b10000000000 :
b100000 9
0+
08
0%
03
b10010000011001000010000100100000 4
1!
#630000
b1111110 .
0!
b1111110 $
b11100110110011110011100111001 #
1&
#635000
b10000000000 :
b11010101011110000100010110101010 4
1+
18
1%
13
b11100110110011110011100111001 (
b11100110110011110011100111001 1
b100000 9
1!
#640000
0!
0&
#645000
b10000000000 :
b100000 9
0+
08
0%
03
b1001110110011001100110010011101 4
1!
#650000
b11111 .
1-
0!
b11111 $
1&
b1111111111 "
#655000
b10000000000 :
b1001011001000000011111010010110 4
1+
18
b1 5
b1 /
1%
13
b0 (
b0 1
b100000 9
1!
#660000
0!
0&
#665000
0+
08
0%
03
1!
#670000
b1111000 .
0!
b1111000 $
1&
b11 "
#675000
b10000000000 :
1+
18
b10 5
b10 /
1%
13
b100000 9
1!
#680000
0!
0&
#685000
0+
08
0%
03
1!
#690000
b111111 .
0,
0!
b111111 $
1&
b10 "
#695000
b10000000000 :
1+
18
b11111111111111111111111111011110 6
b11 5
b11 /
1%
13
b11111111111111111111111111011110 7
b100000 9
1!
#700000
0!
0&
#705000
0+
08
0%
03
1!
#710000
b10000110 .
0!
b10000110 $
1&
b1111111110 "
#715000
b10000000000 :
1+
18
b11111111111111111111111111011110 0
b11111111111111111111111101010110 6
b100 5
b100 /
1%
13
b11111111111111111111111101010110 7
b100000 9
1!
#720000
0!
0&
#725000
b11111111111111111111111111011110 (
b11111111111111111111111111011110 1
0+
08
0%
03
1!
#730000
b11111010 .
0!
b11111010 $
1&
#735000
b10000000000 :
1+
18
b11111111111111111111111101010110 0
b11111111111111111111110110111110 6
b101 5
b101 /
1%
13
b11111111111111111111110110111110 7
b100000 9
1!
#740000
0!
0&
#745000
b11111111111111111111111101010110 (
b11111111111111111111111101010110 1
0+
08
0%
03
1!
#750000
b10100011 .
1,
0!
b10100011 $
1&
b1111111111 "
#755000
b10000000000 :
1+
18
b11111111111111111111110110111110 0
b11111111111111111111100101111110 6
b110 5
b110 /
1%
13
b11111111111111111111100101111110 7
b100000 9
1!
#760000
0!
0&
#765000
b11111111111111111111110110111110 (
b11111111111111111111110110111110 1
0+
08
0%
03
1!
#770000
b1011111 .
0-
0,
0!
b1011111 $
1&
b0 "
#775000
b10000000000 :
1+
18
b0 5
b0 /
1%
13
b0 (
b0 1
b100000 9
1!
#780000
0!
0&
#785000
b10000000000 :
b100000 9
0+
08
0%
03
b1001100000111011100000010011 4
1!
#790000
b11001011 .
1-
0!
b11001011 $
1&
b1111111110 "
#795000
b10000000000 :
b110101111000011100000001101 4
1+
18
b11111111111111111111100101111110 0
b0 6
b1 5
b1 /
1%
13
b11111111111111111111110110111110 (
b11111111111111111111110110111110 1
b0 7
b100000 9
1!
#800000
0!
0&
#805000
b11111111111111111111100101111110 (
b11111111111111111111100101111110 1
0+
08
0%
03
1!
#810000
b101001 .
0-
1,
0!
b101001 $
b11101101010100110110110011011010 #
1&
b1111111101 "
#815000
b10000000000 :
1+
18
b0 5
b0 /
1%
13
b11101101010100110110110011011010 (
b11101101010100110110110011011010 1
b100000 9
1!
#820000
0!
0&
#825000
b10000000000 :
b100000 9
0+
08
0%
03
b101001101001111101011001010011 4
1!
#830000
b1100101 .
0!
b1100101 $
b11101111101111101001010011011111 #
1&
#835000
b10000000000 :
b10110101100111111101110101101011 4
1+
18
1%
13
b11101111101111101001010011011111 (
b11101111101111101001010011011111 1
b100000 9
1!
#840000
0!
0&
#845000
b10000000000 :
b100000 9
0+
08
0%
03
b1101010101001100010101011010101 4
1!
#850000
b1111001 .
0,
0!
b1111001 $
1&
b0 "
#855000
b10000000000 :
b1000101110100101000000010 4
1+
18
1%
13
b0 (
b0 1
b100000 9
1!
#860000
0!
0&
#865000
b10000000000 :
b100000 9
0+
08
0%
03
b1010111010101100011111010101110 4
1!
#870000
b101010 .
1-
1,
0!
b101010 $
1&
b11 "
#875000
b10000000000 :
b10001110111111111110100100011101 4
1+
18
b0 0
b1 5
b1 /
1%
13
b11111111111111111111100101111110 (
b11111111111111111111100101111110 1
b100000 9
1!
#880000
0!
0&
#885000
b0 (
b0 1
0+
08
0%
03
1!
#890000
b11011100 .
0,
0!
b11011100 $
1&
b1111111110 "
#895000
b10000000000 :
1+
18
b10 5
b10 /
1%
13
b100000 9
1!
#900000
0!
0&
#905000
0+
08
0%
03
1!
#910000
b11000011 .
0!
b11000011 $
1&
b10 "
#915000
b10000000000 :
1+
18
b11111111111111111111111111011110 6
b11 5
b11 /
1%
13
b11111111111111111111111111011110 7
b100000 9
1!
#920000
0!
0&
#925000
0+
08
0%
03
1!
#930000
b1100111 .
0!
b1100111 $
1&
b1111111110 "
#935000
b10000000000 :
1+
18
b11111111111111111111111111011110 0
b11111111111111111111111101010110 6
b100 5
b100 /
1%
13
b11111111111111111111111101010110 7
b100000 9
1!
#940000
0!
0&
#945000
b11111111111111111111111111011110 (
b11111111111111111111111111011110 1
0+
08
0%
03
1!
#950000
b111000 .
0-
1,
0!
b111000 $
b11011100001010111100010010111000 #
1&
b1 "
#955000
b10000000000 :
1+
18
b0 5
b0 /
1%
13
b11011100001010111100010010111000 (
b11011100001010111100010010111000 1
b100000 9
1!
#960000
0!
0&
#965000
b10000000000 :
b100000 9
0+
08
0%
03
b1100111110001010111001011001111 4
1!
#970000
b10010100 .
1-
0!
b10010100 $
1&
b11 "
#975000
b10000000000 :
b10010001100001000100100100100011 4
1+
18
b11111111111111111111111101010110 0
b0 6
b1 5
b1 /
1%
13
b11111111111111111111111111011110 (
b11111111111111111111111111011110 1
b0 7
b100000 9
1!
#980000
0!
0&
#985000
b11111111111111111111111101010110 (
b11111111111111111111111101010110 1
0+
08
0%
03
1!
#990000
b1011001 .
0!
b1011001 $
1&
#995000
b10000000000 :
1+
18
b0 0
b10 5
b10 /
1%
13
b100000 9
1!
#1000000
0!
0&
#1005000
b0 (
b0 1
0+
08
0%
03
1!
#1010000
b11011001 .
0-
0!
b11011001 $
b10111011010001011110001001110110 #
1&
b1111111101 "
#1015000
b10000000000 :
1+
18
b0 5
b0 /
1%
13
b10111011010001011110001001110110 (
b10111011010001011110001001110110 1
b100000 9
1!
#1020000
0!
0&
