simple_pim/example_cfu_pim_v/cfu.v
module cfu#(
    parameter PIM_ADDR_BEGIN = 'h000,
    parameter DWIDTH = 32,   // DATA WIDTH
    parameter AWIDTH = 10,    // ADDRESS WIDTH
    parameter PWIDTH = 32,   // PIM WIDTH
    parameter PDEPTH = (1 << AWIDTH) // PIM DEPTH
)(
    // output [PWIDTH-1:0] q,
    // output [DWIDTH-1:0] mac_out,
    input [PWIDTH-1:0] cmd_payload_inputs_1,    // not using
    input [PWIDTH-1:0] cmd_payload_inputs_0,    
    input [AWIDTH-1:0] cmd_payload_function_id,
    // input [PDEPTH-1:0] rwl,
    input clk,
    input reset,
    input cmd_valid,
    output cmd_ready,
    output rsp_valid,
    input rsp_ready,
    output rsp_payload_response_ok,
    output [DWIDTH-1:0] rsp_payload_outputs_0
);

    reg [PWIDTH-1:0] mem [PIM_ADDR_BEGIN:PIM_ADDR_BEGIN+PDEPTH-1];
    reg [DWIDTH-1:0] adc_out [0:PWIDTH-1];
    reg [4:0] shift_cnt;
    reg [DWIDTH-1:0] acc_result [0:PWIDTH-1];
    reg [DWIDTH-1:0] sum_acc_result;
    reg [DWIDTH-1:0] mac_out_reg;
    reg [PWIDTH-1:0] q_reg;
    reg [DWIDTH-1:0] out;

    wire p_en, w_en;
    assign p_en = cmd_payload_function_id[1];
    assign w_en = cmd_payload_function_id[0];

    wire [7:0] mem_addr = cmd_payload_function_id[AWIDTH-1:AWIDTH-8];

    assign rsp_valid = cmd_valid;
    assign cmd_ready = rsp_ready;
    assign rsp_payload_response_ok = 1'b1;

    integer i, j;

	initial begin 
	     for (i = PIM_ADDR_BEGIN; i < PIM_ADDR_BEGIN + PDEPTH; i = i+1) begin
                mem[i] = 0; // Use non-blocking assignment
         end
    end	

	reg [DWIDTH-1:0] temp_sum_acc_result;

    reg [PDEPTH-1:0] rwl;
    always @(posedge clk or negedge reset) begin
        if (reset) begin
            rwl <= 0;  // Reset rwl
        end else begin
            rwl <= $random;  // Generate random rwl
        end
    end
    
	always @(posedge clk or negedge reset) begin
        if (reset) begin
            shift_cnt <= 0;
            for (i = 0; i < PWIDTH; i = i+1) begin
                acc_result[i] <= 0;
                adc_out[i] <= 0; // Initialize adc_out
            end
            sum_acc_result <= 0;
            q_reg <= 0;
            mac_out_reg <= 0;
        end
        else begin
            if (!p_en) begin // Processing Disabled -> Memory operation
                if (w_en) begin // Memory Write Enable
                    mem[mem_addr] <= cmd_payload_inputs_0;
                end
                else begin // Memory Read Enable
                    q_reg <= mem[mem_addr];
                end
                // Initialize accumulation
                shift_cnt <= 0;
                for (i = 0; i < PWIDTH; i = i+1) begin
                    acc_result[i] <= 0;
                end
            end
            else begin // Processing Enabled -> MAC operation
                for (i = 0; i < PWIDTH; i = i+1) begin
                    acc_result[i] <= (shift_cnt == 0) ? adc_out[i] : acc_result[i] + (adc_out[i] << shift_cnt);
		            $display("acc_result[%d]: %h <- shift_cnt: %b", i, acc_result[i], shift_cnt);
		        end
                shift_cnt <= shift_cnt + 1;

                // Initialize sum_acc_result
                sum_acc_result <= 0;
                
                temp_sum_acc_result = 0;
                for (i = 0; i < PWIDTH; i = i+1) begin
                    temp_sum_acc_result = temp_sum_acc_result + acc_result[i];
                    sum_acc_result <= temp_sum_acc_result;
                    $display("temp_sum_acc_result: %h", temp_sum_acc_result);
                    $display("sum_acc_result: %h", sum_acc_result);
                end
                mac_out_reg <= sum_acc_result;
            end
        end
    end

    // assign q = q_reg;
    // assign mac_out = mac_out_reg;

    always @(*) begin
        for (i = 0; i < PWIDTH; i = i+1) begin
            adc_out[i] = 0;
            for (j = 0; j < PDEPTH; j = j+1) begin
                adc_out[i] = adc_out[i] + ({PWIDTH{mem[PIM_ADDR_BEGIN + j][i]}} & {PWIDTH{rwl[j]}});
            end
        end
	end

    always @(posedge clk or posedge reset) begin
        if(reset) out <= 32'd0;
        else begin
	    if (p_en) begin
		out <= mac_out_reg;
		$display("MacOut: %h", mac_out_reg); // p_en, w_en = b'10 or 11
	    end
            else begin
	        if (w_en) begin
		    out <= mem[mem_addr];
		    $display("Write: %h", mem[mem_addr]); // p_en, w_en = b'01
	        end
	        else begin 
		    out <= q_reg;
		    $display("Read: %h", q_reg); // p_en, w_en = b'00
	        end
            end
        end
    end

    assign rsp_payload_outputs_0 = out;
	
endmodule

cfu_test/sim/cfu_test/src/testbench.v
module tb_pim_model;

    parameter DWIDTH = 32;
    parameter AWIDTH = 10;
    parameter PWIDTH = 32;
    parameter PDEPTH = 256;

    reg clk;
    reg reset;

    reg [PWIDTH-1:0] d;
    reg [AWIDTH-1:0] addr;
    reg [PDEPTH-1:0] rwl;
    // reg w_en;
    // reg p_en;
    wire p_en = addr[1];
    wire w_en = addr[0];

    wire [7:0] mem_addr = addr[AWIDTH-1:AWIDTH-8];

    reg cmd_valid;
    reg rsp_ready;

    wire [PWIDTH-1:0] q;
    wire [DWIDTH-1:0] mac_out;
    wire cmd_ready;
    wire rsp_valid;

    wire [DWIDTH-1:0] out;

    integer i;

    reg [AWIDTH-1:0] write_addrs [0:PDEPTH-1];
    integer write_index;

    cfu #(
        .PIM_ADDR_BEGIN(10'h000),
        .DWIDTH(DWIDTH),
        .AWIDTH(AWIDTH),
        .PWIDTH(PWIDTH),
        .PDEPTH(PDEPTH)
    ) dut (
        // .q(q),
        // .mac_out(mac_out),
        .cmd_payload_inputs_0(d),
        .cmd_payload_inputs_1(32'd0),
        .cmd_payload_function_id(addr),
        // .rwl(rwl),
        // .w_en(w_en),
        // .p_en(p_en),
        .clk(clk),
        .reset(reset),
        .cmd_valid(cmd_valid),
        .cmd_ready(cmd_ready),
        .rsp_valid(rsp_valid),
        .rsp_ready(rsp_ready),
        .rsp_payload_outputs_0(out)
    );

    initial begin
        clk = 0;
        forever #5 clk = ~clk; 
    end

    integer j;
    reg found;
    
    // Test stimulus
    initial begin
        // Initialize signals
        clk = 0;
        reset = 1;
        d = 0;
        addr = 0;
        // rwl = 0;
        // w_en = 0;
        // p_en = 0;
        cmd_valid = 0;
        rsp_ready = 0;

        // Reset the design
        #10 reset = 0;

        // Write some data to memory
        for (i = 0; i < PDEPTH; i = i + 1) begin
            @(posedge clk);
            d = $random;
            addr = $random % 256;

            // w_en = $random % 2;
            // p_en = $random % 2;

            // rwl = $random;

            // if (!w_en && !p_en) begin
            if (!w_en && !p_en) begin
                $display("Read !!");
                found = 0;
    
                for (j = 0; j < write_index; j = j + 1) begin
                    if (write_addrs[j] == mem_addr) begin
                        found = 1;
                    	$display("existing address %h", mem_addr);
                    end
                end
                if (!found) begin
                    $display("No data at address %h", mem_addr);
                end
                // $display("mem[%h] -> %h", addr, q);
                $display("[out ver.] mem[%h] -> %h", mem_addr, out);
            end
            else if (w_en && !p_en) begin
                $display("Write !!");
                write_addrs[write_index] = mem_addr;
                write_index = write_index + 1;
                // $display("mem[%h] <- %h", addr, d);
                $display("[out ver.] mem[%h] <- %h", mem_addr, out);
            end else begin
                $display("MAC_OUT !!");
                // $display("Processing value %h", mac_out);
                $display("[out ver.] Processing value %h", out);
            end
            $display("=============================");
            // rwl = $random & ((1 << PDEPTH) - 1);
            @(posedge clk);
        end
        #100;

        $finish;
    end

    initial begin
        $dumpvars(2, dut);
        $dumpfile("pim_module.vcd");
    end

endmodule

simple_pim/model/cfu/sim/cfu_test/dump.vcd
$date
	Thu Sep 19 17:30:33 2024
$end
$version
	Icarus Verilog
$end
$timescale
	1s
$end
$scope module tb_pim_model $end
$scope module dut $end
$var wire 1 ! clk $end
$var wire 10 " cmd_payload_function_id [9:0] $end
$var wire 32 # cmd_payload_inputs_0 [31:0] $end
$var wire 32 $ cmd_payload_inputs_1 [31:0] $end
$var wire 1 % cmd_ready $end
$var wire 1 & cmd_valid $end
$var wire 1 ' reset $end
$var wire 32 ( rsp_payload_outputs_0 [31:0] $end
$var wire 1 ) rsp_payload_response_ok $end
$var wire 1 * rsp_ready $end
$var wire 1 + rsp_valid $end
$var wire 1 , w_en $end
$var wire 1 - p_en $end
$var wire 8 . mem_addr [7:0] $end
$var reg 32 / mac_out_reg [31:0] $end
$var reg 32 0 out [31:0] $end
$var reg 32 1 q_reg [31:0] $end
$var reg 256 2 rwl [255:0] $end
$var reg 5 3 shift_cnt [4:0] $end
$var reg 32 4 sum_acc_result [31:0] $end
$var reg 32 5 temp_sum_acc_result [31:0] $end
$var integer 32 6 i [31:0] $end
$var integer 32 7 j [31:0] $end
$upscope $end
$upscope $end
$enddefinitions $end
#0
$dumpvars
b100000000 7
b100000 6
bx 5
bx 4
bx 3
bx 2
bx 1
b0 0
bx /
b0 .
0-
0,
0+
0*
1)
b0 (
1'
0&
0%
b0 $
b0 #
b0 "
0!
$end
#5
b100000000 7
b0 2
b0 /
b0 1
b0 4
b0 3
b100000 6
1!
#10
b100000000 7
b10010000101010011010100100100 2
b100000 6
0!
0'
#15
b100000000 7
b1111111111111111111111111111111111111111111111111111111111111111111111111111111111111111111111111111111111111111111111111111111111111111111111111111111111111111111111111111111111111111111111111111111111111111111111111111111110110001111100000101011001100011 2
1,
b11000010 .
b100000 6
b1100001001 "
b11000000100010010101111010000001 #
1!
#20
0!
#25
b100000000 7
b110101110010111101100001101 2
b100000 6
1!
#30
0!
#35
b100000000 7
b11000000100010010101111010000001 (
b11000000100010010101111010000001 0
b1111111111111111111111111111111111111111111111111111111111111111111111111111111111111111111111111111111111111111111111111111111111111111111111111111111111111111111111111111111111111111111111111111111111111111111111111111111110001001001101110101001000010010 2
b11011001 .
b100000 6
b1101100101 "
b1000110110111111001100110001101 #
1!
#40
0!
#45
b100000000 7
b0 (
b0 0
b111100111110001100000001 2
b100000 6
1!
#50
0!
#55
b100000000 7
b1000110110111111001100110001101 (
b1000110110111111001100110001101 0
b11110100011011100110100111101 2
1-
0,
b11101 .
b100000 6
b1110110 "
b110110101111100110100001101 #
1!
#60
0!
#65
b100000000 7
b0 (
b0 0
b1 3
b1110110110101000101011111101101 2
b0 5
b100000 6
1!
#70
0!
#75
b100000000 7
b1111111111111111111111111111111111111111111111111111111111111111111111111111111111111111111111111111111111111111111111111111111111111111111111111111111111111111111111111111111111111111111111111111111111111111111111111111111111100011001101110010010011000110 2
b10 3
0-
1,
b111110 .
b100000 6
b11111001 "
b1000110001011011111011110001100 #
1!
#80
0!
#85
b100000000 7
b0 3
b1111111111111111111111111111111111111111111111111111111111111111111111111111111111111111111111111111111111111111111111111111111111111111111111111111111111111111111111111111111111111111111111111111111111111111111111111111111111100010111101111000010011000101 2
b100000 6
1!
#90
0!
#95
b100000000 7
b1000110001011011111011110001100 (
b1000110001011011111011110001100 0
b1111111111111111111111111111111111111111111111111111111111111111111111111111111111111111111111111111111111111111111111111111111111111111111111111111111111111111111111111111111111111111111111111111111111111111111111111111111110111011110100100111001001110111 2
b111001 .
b100000 6
b11100101 "
b11010101000100111101001010101010 #
1!
#100
0!
#105
b100000000 7
b0 (
b0 0
b1111111111111111111111111111111111111111111111111111111111111111111111111111111111111111111111111111111111111111111111111111111111111111111111111111111111111111111111111111111111111111111111111111111111111111111111111111111110001001001100101101011000010010 2
b100000 6
1!
#110
0!
#115
b100000000 7
b11010101000100111101001010101010 (
b11010101000100111101001010101010 0
b1111111111111111111111111111111111111111111111111111111111111111111111111111111111111111111111111111111111111111111111111111111111111111111111111111111111111111111111111111111111111111111111111111111111111111111111111111111111100111011101101001011011001110 2
1-
0,
b111100 .
b100000 6
b11110010 "
b1000111111011001101101110001111 #
1!
#120
0!
#125
b100000000 7
b0 (
b0 0
b1 3
b1111111111111111111111111111111111111111111111111111111111111111111111111111111111111111111111111111111111111111111111111111111111111111111111111111111111111111111111111111111111111111111111111111111111111111111111111111111111110100000000000111101011101000 2
b100000 6
1!
#130
0!
#135
b100000000 7
b1111111111111111111111111111111111111111111111111111111111111111111111111111111111111111111111111111111111111111111111111111111111111111111111111111111111111111111111111111111111111111111111111111111111111111111111111111111111011110100011100010100010111101 2
b11111111111111111111111110111010 4
b10 3
0-
b10111 .
b11111111111111111111111110111010 5
b100000 6
b1011100 "
b11100010110010100100111011000101 #
1!
#140
0!
#145
b100000000 7
b0 3
b1111111111111111111111111111111111111111111111111111111111111111111111111111111111111111111111111111111111111111111111111111111111111111111111111111111111111111111111111111111111111111111111111111111111111111111111111111111110010110101010110101100000101101 2
b100000 6
1!
#150
0!
#155
b100000000 7
b101011100111000011100001010 2
1-
1,
b11011000 .
b100000 6
b1101100011 "
b10110010101001110010011001100101 #
1!
#160
0!
#165
b100000000 7
b11111111111111111111111110111010 /
b0 4
b1 3
b1111111111111111111111111111111111111111111111111111111111111111111111111111111111111111111111111111111111111111111111111111111111111111111111111111111111111111111111111111111111111111111111111111111111111111111111111111111111000000001110110010001010000000 2
b0 5
b100000 6
1!
#170
0!
#175
b100000000 7
b11111111111111111111111110111010 (
b11111111111111111111111110111010 0
b1111111111111111111111111111111111111111111111111111111111111111111111111111111111111111111111111111111111111111111111111111111111111111111111111111111111111111111111111111111111111111111111111111111111111111111111111111111111001110110011001100110010011101 2
b0 /
b10 3
0,
b101010 .
b100000 6
b10101010 "
b10000011001000010000100100000 #
1!
#180
0!
#185
b100000000 7
b0 (
b0 0
b11111111111111111111111101110100 4
b11 3
b1111111111111111111111111111111111111111111111111111111111111111111111111111111111111111111111111111111111111111111111111111111111111111111111111111111111111111111111111111111111111111111111111111111111111111111111111111111111001011001000000011111010010110 2
b11111111111111111111111101110100 5
b100000 6
1!
#190
0!
#195
b100000000 7
b1111111111111111111111111111111111111111111111111111111111111111111111111111111111111111111111111111111111111111111111111111111111111111111111111111111111111111111111111111111111111111111111111111111111111111111111111111111110101001101001111101011001010011 2
b11111111111111111111111101110100 /
b11111111111111111111111001011100 4
b100 3
0-
1,
b11000011 .
b11111111111111111111111001011100 5
b100000 6
b1100001101 "
b10001001100000111011100000010011 #
1!
#200
0!
#205
b100000000 7
b0 3
b110101100111111101110101101011 2
b100000 6
1!
#210
0!
#215
b100000000 7
b10001001100000111011100000010011 (
b10001001100000111011100000010011 0
b1111111111111111111111111111111111111111111111111111111111111111111111111111111111111111111111111111111111111111111111111111111111111111111111111111111111111111111111111111111111111111111111111111111111111111111111111111111111010111010101100011111010101110 2
1-
0,
b11000000 .
b100000 6
b1100000010 "
b11101010101001100010101011010101 #
1!
#220
0!
#225
b100000000 7
b11111111111111111111111101110100 (
b11111111111111111111111101110100 0
b11111111111111111111111001011100 /
b0 4
b1 3
b1110111111111110100100011101 2
b0 5
b100000 6
1!
#230
0!
#235
b100000000 7
b11111111111111111111111001011100 (
b11111111111111111111111001011100 0
b101000010010110010100001010 2
b0 /
b11111111111111111111111110101001 4
b10 3
1,
b1000 .
b11111111111111111111111110101001 5
b100000 6
b100011 "
b11100111110001010111001011001111 #
1!
#240
0!
#245
b100000000 7
b0 (
b0 0
b11111111111111111111111110101001 /
b11111111111111111111111110101001 4
b11 3
b1111111111111111111111111111111111111111111111111111111111111111111111111111111111111111111111111111111111111111111111111111111111111111111111111111111111111111111111111111111111111111111111111111111111111111111111111111111111100101011100110000101011001010 2
b11111111111111111111111110101001 5
b100000 6
1!
#250
0!
#255
b100000000 7
b11111111111111111111111110101001 (
b11111111111111111111111110101001 0
b1000101001011100110000110001010 2
b11111111111111111111111110101001 4
b100 3
0,
b111100 .
b11111111111111111111111110101001 5
b100000 6
b11110010 "
b10011110001100010100110000111100 #
1!
#260
0!
#265
b100000000 7
b11111111111111111111110011110001 4
b101 3
b100000110001001011001101000001 2
b11111111111111111111110011110001 5
b100000 6
1!
#270
0!
#275
b100000000 7
b1111111111111111111111111111111111111111111111111111111111111111111111111111111111111111111111111111111111111111111111111111111111111111111111111111111111111111111111111111111111111111111111111111111111111111111111111111111111000100100010100001001010001001 2
b11111111111111111111110011110001 /
b11111111111111111111110011110001 4
b110 3
0-
b11110 .
b11111111111111111111110011110001 5
b100000 6
b1111000 "
b11101100010010110011010011011000 #
1!
#280
0!
#285
b100000000 7
b0 (
b0 0
b0 3
b1110101110001010000110111101011 2
b100000 6
1!
#290
0!
#295
b100000000 7
b1010111000101010001001110101110 2
1-
b110001 .
b100000 6
b11000110 "
b1011011000000100110010110110110 #
1!
#300
0!
#305
b100000000 7
b11111111111111111111110011110001 (
b11111111111111111111110011110001 0
b0 4
b1 3
b1111111111111111111111111111111111111111111111111111111111111111111111111111111111111111111111111111111111111111111111111111111111111111111111111111111111111111111111111111111111111111111111111111111111111111111111111111111111011110011101010000001010111100 2
b0 5
b100000 6
1!
#310
0!
#315
b100000000 7
b1111111111111111111111111111111111111111111111111111111111111111111111111111111111111111111111111111111111111111111111111111111111111111111111111111111111111111111111111111111111111111111111111111111111111111111111111111111110111000100101111011111001110001 2
b0 /
b10 3
1,
b11000010 .
b100000 6
b1100001011 "
b10101000011111101110100101010 #
1!
#320
0!
#325
b100000000 7
b0 (
b0 0
b11111111111111111111111101010010 4
b11 3
b1000010111100100100000110000101 2
b11111111111111111111111101010010 5
b100000 6
1!
#330
0!
#335
b100000000 7
b11101000001100011001100111010 2
b11111111111111111111111101010010 /
b11111111111111111111110111110110 4
b100 3
b11001110 .
b11111111111111111111110111110110 5
b100000 6
b1100111011 "
b100111111100100101010101001111 #
1!
#340
0!
#345
b100000000 7
b11111111111111111111111101010010 (
b11111111111111111111111101010010 0
b11111111111111111111110111110110 /
b11111111111111111111110111110110 4
b101 3
b1111111111111111111111111111111111111111111111111111111111111111111111111111111111111111111111111111111111111111111111111111111111111111111111111111111111111111111111111111111111111111111111111111111111111111111111111111111110111111001000110011001001111110 2
b11111111111111111111110111110110 5
b100000 6
1!
#350
0!
#355
b100000000 7
b11111111111111111111110111110110 (
b11111111111111111111110111110110 0
b1101100100111000100101111011001 2
b11111111111111111111110111110110 4
b110 3
0-
b111100 .
b11111111111111111111110111110110 5
b100000 6
b11110001 "
b1010101010100100101100010101 #
1!
#360
0!
#365
b100000000 7
b0 (
b0 0
b0 3
b110001001000110000011101100010 2
b100000 6
1!
#370
0!
#375
b100000000 7
b1010101010100100101100010101 (
b1010101010100100101100010101 0
b1000111101110011010000110001111 2
1-
b100111 .
b100000 6
b10011111 "
b100110001101011111101101001100 #
1!
#380
0!
#385
b100000000 7
b11111111111111111111110111110110 (
b11111111111111111111110111110110 0
b0 4
b1 3
b1111100011011011010100111111000 2
b0 5
b100000 6
1!
#390
0!
#395
b100000000 7
b1111111111111111111111111111111111111111111111111111111111111111111111111111111111111111111111111111111111111111111111111111111111111111111111111111111111111111111111111111111111111111111111111111111111111111111111111111111110101110011111011001010001011100 2
b0 /
b10 3
b11100111 .
b100000 6
b1110011111 "
b11011011110011010110000010110111 #
1!
#400
0!
#405
b100000000 7
b0 (
b0 0
b11 3
b1111111111111111111111111111111111111111111111111111111111111111111111111111111111111111111111111111111111111111111111111111111111111111111111111111111111111111111111111111111111111111111111111111111111111111111111111111111110101101110010111100000001011011 2
b100000 6
1!
#410
0!
#415
b100000000 7
b1111111111111111111111111111111111111111111111111111111111111111111111111111111111111111111111111111111111111111111111111111111111111111111111111111111111111111111111111111111111111111111111111111111111111111111111111111111111101000001000110011111011010000 2
b11111111111111111111111001100000 4
b100 3
0-
b11010010 .
b11111111111111111111111001100000 5
b100000 6
b1101001001 "
b1000100110111100011011110001001 #
1!
#420
0!
#425
b100000000 7
b0 3
b1111111111111111111111111111111111111111111111111111111111111111111111111111111111111111111111111111111111111111111111111111111111111111111111111111111111111111111111111111111111111111111111111111111111111111111111111111111111101011111111101100000011010111 2
b100000 6
1!
#430
0!
#435
b100000000 7
b1000100110111100011011110001001 (
b1000100110111100011011110001001 0
b110000111010111111100001100 2
1-
0,
b100101 .
b100000 6
b10010110 "
b10101000110001111111110001010001 #
1!
#440
0!
#445
b100000000 7
b0 (
b0 0
b11111111111111111111111001100000 /
b0 4
b1 3
b1111111111111111111111111111111111111111111111111111111111111111111111111111111111111111111111111111111111111111111111111111111111111111111111111111111111111111111111111111111111111111111111111111111111111111111111111111111111100001001011001100111011000010 2
b0 5
b100000 6
1!
#450
0!
#455
b100000000 7
b11111111111111111111111001100000 (
b11111111111111111111111001100000 0
b11110111100101110110100111101 2
b0 /
b10 3
1,
b11011101 .
b100000 6
b1101110111 "
b1100100010101111110110111001000 #
1!
#460
0!
#465
b100000000 7
b0 (
b0 0
b11111111111111111111111100001110 4
b11 3
b1001000011001101101100010010 2
b11111111111111111111111100001110 5
b100000 6
1!
#470
0!
#475
b100000000 7
b11100110110011110011100111001 2
b11111111111111111111111100001110 /
b11111111111111111111111100001110 4
b100 3
0-
b11011 .
b11111111111111111111111100001110 5
b100000 6
b1101101 "
b10111111000001010000000001111110 #
1!
#480
0!
#485
b100000000 7
b0 3
b1111110100101000111100011111 2
b100000 6
1!
#490
0!
#495
b100000000 7
b10111111000001010000000001111110 (
b10111111000001010000000001111110 0
b1111111111111111111111111111111111111111111111111111111111111111111111111111111111111111111111111111111111111111111111111111111111111111111111111111111111111111111111111111111111111111111111111111111111111111111111111111111110111100000101001000100001111000 2
b100001 .
b100000 6
b10000101 "
b11101001111010111111011011010011 #
1!
#500
0!
#505
b100000000 7
b0 (
b0 0
b101101110110100101100101011011 2
b100000 6
1!
#510
0!
#515
b100000000 7
b11101001111010111111011011010011 (
b11101001111010111111011011010011 0
b10101000011001010111100101010 2
1-
b11001111 .
b100000 6
b1100111111 "
b100100100010110100101101001001 #
1!
#520
0!
#525
b100000000 7
b11111111111111111111111100001110 (
b11111111111111111111111100001110 0
b0 4
b1 3
b101100000101010110001101011000 2
b0 5
b100000 6
1!
#530
0!
#535
b100000000 7
b1111111111111111111111111111111111111111111111111111111111111111111111111111111111111111111111111111111111111111111111111111111111111111111111111111111111111111111111111111111111111111111111111111111111111111111111111111111111001110001011111111001010011100 2
b0 /
b10 3
0,
b11100011 .
b100000 6
b1110001110 "
b11000011001111110011100010000110 #
1!
#540
0!
#545
b100000000 7
b0 (
b0 0
b11111111111111111111111111010100 4
b11 3
b1111101001101011001100111111010 2
b11111111111111111111111111010100 5
b100000 6
1!
#550
0!
#555
b100000000 7
b1111111111111111111111111111111111111111111111111111111111111111111111111111111111111111111111111111111111111111111111111111111111111111111111111111111111111111111111111111111111111111111111111111111111111111111111111111111111010001100010111011010010100011 2
b11111111111111111111111111010100 /
b11111111111111111111110101100100 4
b100 3
1,
b11100 .
b11111111111111111111110101100100 5
b100000 6
b1110011 "
b10010011011111011011110000100110 #
1!
#560
0!
#565
b100000000 7
b11111111111111111111111111010100 (
b11111111111111111111111111010100 0
b11111111111111111111110101100100 /
b11111111111111111111110010110100 4
b101 3
b1111111111111111111111111111111111111111111111111111111111111111111111111111111111111111111111111111111111111111111111111111111111111111111111111111111111111111111111111111111111111111111111111111111111111111111111111111111110010111100110011010100000101111 2
b11111111111111111111110010110100 5
b100000 6
1!
#570
0!
#575
b100000000 7
b11111111111111111111110101100100 (
b11111111111111111111110101100100 0
b100010001010010000110101000100 2
b11111111111111111111110010110100 /
b11111111111111111111010001010100 4
b110 3
b11010111 .
b11111111111111111111010001010100 5
b100000 6
b1101011111 "
b11011001110100101001001010110011 #
1!
#580
0!
#585
b100000000 7
b11111111111111111111110010110100 (
b11111111111111111111110010110100 0
b11111111111111111111010001010100 /
b11111111111111111110001110010100 4
b111 3
b1111011111110001111110111110111 2
b11111111111111111110001110010100 5
b100000 6
1!
#590
0!
#595
b100000000 7
b11111111111111111111010001010100 (
b11111111111111111111010001010100 0
b101101001010001101101101011010 2
b11111111111111111110001110010100 /
b11111111111111111110001110010100 4
b1000 3
0,
b11111001 .
b11111111111111111110001110010100 5
b100000 6
b1111100110 "
b11100101100110110011011011001011 #
1!
#600
0!
#605
b100000000 7
b11111111111111111110001110010100 (
b11111111111111111110001110010100 0
b11111111111111111101100010010100 4
b1001 3
b10100110011111100000100101001 2
b11111111111111111101100010010100 5
b100000 6
1!
#610
0!
#615
b100000000 7
b1111111111111111111111111111111111111111111111111111111111111111111111111111111111111111111111111111111111111111111111111111111111111111111111111111111111111111111111111111111111111111111111111111111111111111111111111111111110110010100111111011011001100101 2
b11111111111111111101100010010100 /
b11111111111111111100001010010100 4
b1010 3
b11110110 .
b11111111111111111100001010010100 5
b100000 6
b1111011010 "
b11110110100000101110001011101101 #
1!
#620
0!
#625
b100000000 7
b11111111111111111101100010010100 (
b11111111111111111101100010010100 0
b11111111111111111100001010010100 /
b11111111111111111100001010010100 4
b1011 3
b1111111111111111111111111111111111111111111111111111111111111111111111111111111111111111111111111111111111111111111111111111111111111111111111111111111111111111111111111111111111111111111111111111111111111111111111111111111111011010100010101110001010110101 2
b11111111111111111100001010010100 5
b100000 6
1!
#630
0!
#635
b100000000 7
b11111111111111111100001010010100 (
b11111111111111111100001010010100 0
b100010001100011111111101000100 2
b11111111111111011010101010010100 4
b1100 3
0-
1,
b11110 .
b11111111111111011010101010010100 5
b100000 6
b1111001 "
b11101111101111101001010011011111 #
1!
#640
0!
#645
b100000000 7
b0 (
b0 0
b0 3
b1111111111111111111111111111111111111111111111111111111111111111111111111111111111111111111111111111111111111111111111111111111111111111111111111111111111111111111111111111111111111111111111111111111111111111111111111111111111101000011101000000110011010000 2
b100000 6
1!
#650
0!
#655
b100000000 7
b11101111101111101001010011011111 (
b11101111101111101001010011011111 0
b111011011111100111100001110 2
1-
b101010 .
b100000 6
b10101011 "
b10101000010010000101100101010 #
1!
#660
0!
#665
b100000000 7
b11111111111111111100001010010100 (
b11111111111111111100001010010100 0
b11111111111111011010101010010100 /
b0 4
b1 3
b1101110010111011010110111011100 2
b0 5
b100000 6
1!
#670
0!
#675
b100000000 7
b11111111111111011010101010010100 (
b11111111111111011010101010010100 0
b1111111111111111111111111111111111111111111111111111111111111111111111111111111111111111111111111111111111111111111111111111111111111111111111111111111111111111111111111111111111111111111111111111111111111111111111111111111111100001111100010000001011000011 2
b0 /
b10 3
0-
b11111111 .
b100000 6
b1111111101 "
b11001101010111101011110010011010 #
1!
#680
0!
#685
b100000000 7
b0 (
b0 0
b0 3
b101011000011101110110101010110 2
b100000 6
1!
#690
0!
#695
b100000000 7
b11001101010111101011110010011010 (
b11001101010111101011110010011010 0
b1111111111111111111111111111111111111111111111111111111111111111111111111111111111111111111111111111111111111111111111111111111111111111111111111111111111111111111111111111111111111111111111111111111111111111111111111111111110000101001100010011010000001010 2
1-
b11011001 .
b100000 6
b1101100111 "
b100111011110011110100101001110 #
1!
#700
0!
#705
b100000000 7
b0 (
b0 0
b1 3
b1011011011011111011100110110110 2
b100000 6
1!
#710
0!
#715
b100000000 7
b1111111111111111111111111111111111111111111111111111111111111111111111111111111111111111111111111111111111111111111111111111111111111111111111111111111111111111111111111111111111111111111111111111111111111111111111111111111111011100001010111100010010111000 2
b11111111111111111111111101101000 4
b10 3
0-
b11110 .
b11111111111111111111111101101000 5
b100000 6
b1111001 "
b10011100000011101000101000111000 #
1!
#720
0!
#725
b100000000 7
b10101000010010000101100101010 (
b10101000010010000101100101010 0
b0 3
b1001010011101001011111110010100 2
b100000 6
1!
#730
0!
#735
b100000000 7
b10011100000011101000101000111000 (
b10011100000011101000101000111000 0
b1111111111111111111111111111111111111111111111111111111111111111111111111111111111111111111111111111111111111111111111111111111111111111111111111111111111111111111111111111111111111111111111111111111111111111111111111111111110101100101101111100101001011001 2
0,
b11000001 .
b100000 6
b1100000100 "
b1001001110001100101110110010011 #
1!
#740
0!
#745
b100000000 7
b0 (
b0 0
b1101101110010110110100111011011 2
b100000 6
1!
#750
0!
#755
b100000000 7
b1111111111111111111111111111111111111111111111111111111111111111111111111111111111111111111111111111111111111111111111111111111111111111111111111111111111111111111111111111111111111111111111111111111111111111111111111111111110110110101001000010011001101101 2
1,
b110110 .
b100000 6
b11011001 "
b10100110111111001101111001001101 #
1!
#760
0!
#765
b100000000 7
b1111111111111111111111111111111111111111111111111111111111111111111111111111111111111111111111111111111111111111111111111111111111111111111111111111111111111111111111111111111111111111111111111111111111111111111111111111111110111011010001011110001001110110 2
b100000 6
1!
#770
0!
#775
b100000000 7
b10100110111111001101111001001101 (
b10100110111111001101111001001101 0
b1001010100100110111000110010101 2
1-
0,
b101101 .
b100000 6
b10110110 "
b1100101001110110100100111001010 #
1!
#780
0!
#785
b100000000 7
b0 (
b0 0
b11111111111111111111111101101000 /
b0 4
b1 3
b1111111111111111111111111111111111111111111111111111111111111111111111111111111111111111111111111111111111111111111111111111111111111111111111111111111111111111111111111111111111111111111111111111111111111111111111111111111110100011000001110001101001000110 2
b0 5
b100000 6
1!
#790
0!
#795
b100000000 7
b11111111111111111111111101101000 (
b11111111111111111111111101101000 0
b110100100110000000011101101001 2
b0 /
b11111111111111111111111111011010 4
b10 3
1,
b111101 .
b11111111111111111111111111011010 5
b100000 6
b11110111 "
b10011101001001101100000100 #
1!
#800
0!
#805
b100000000 7
b0 (
b0 0
b11111111111111111111111111011010 /
b11111111111111111111111010001010 4
b11 3
b1111111111111111111111111111111111111111111111111111111111111111111111111111111111111111111111111111111111111111111111111111111111111111111111111111111111111111111111111111111111111111111111111111111111111111111111111111111111011010011011101011101010110100 2
b11111111111111111111111010001010 5
b100000 6
1!
#810
0!
#815
b100000000 7
b11111111111111111111111111011010 (
b11111111111111111111111111011010 0
b1111111111111111111111111111111111111111111111111111111111111111111111111111111111111111111111111111111111111111111111111111111111111111111111111111111111111111111111111111111111111111111111111111111111111111111111111111111110010110100100000000010000101101 2
b11111111111111111111111010001010 /
b11111111111111111111111010001010 4
b100 3
0-
0,
b1010 .
b11111111111111111111111010001010 5
b100000 6
b101000 "
b1000100000000011000110110001000 #
1!
#820
0!
