simple_pim/model/cfu/sim/EqualTest/fix_test/src/cfu.v
module cfu#(
    parameter PIM_ADDR_BEGIN = 'h000,
    parameter DWIDTH = 32,   // DATA WIDTH
    parameter AWIDTH = 10,    // ADDRESS WIDTH
    parameter PWIDTH = 32,   // PIM WIDTH
    parameter PDEPTH = (1 << AWIDTH) // PIM DEPTH
)(
    input [PWIDTH-1:0] cmd_payload_inputs_0,    // d
    input [PWIDTH-1:0] cmd_payload_inputs_1,    // addr
    input [AWIDTH-1:0] cmd_payload_function_id,
    input clk,
    input reset,
    input cmd_valid,
    output cmd_ready,
    output rsp_valid,
    input rsp_ready,
    output rsp_payload_response_ok,
    output [DWIDTH-1:0] rsp_payload_outputs_0
);

    reg [PWIDTH-1:0] mem [PIM_ADDR_BEGIN:PIM_ADDR_BEGIN+PDEPTH-1];
    reg [DWIDTH-1:0] adc_out [0:PWIDTH-1];
    reg [4:0] shift_cnt;
    reg [DWIDTH-1:0] acc_result [0:PWIDTH-1];
    reg [DWIDTH-1:0] sum_acc_result;
    reg [DWIDTH-1:0] mac_out_reg;
    reg [PWIDTH-1:0] q_reg;
    reg [DWIDTH-1:0] out;

    wire p_en, w_en;
    assign p_en = cmd_payload_function_id[1];
    assign w_en = cmd_payload_function_id[0];

    wire [7:0] mem_addr = cmd_payload_inputs_1[7:0];

    reg ready;
    reg valid;
    assign cmd_ready = ready;
    assign rsp_valid = valid;

    assign rsp_payload_response_ok = 1'b1;

    integer i, j;

    initial begin 
        for (i = PIM_ADDR_BEGIN; i < PIM_ADDR_BEGIN + PDEPTH; i = i+1) begin
            mem[i] = 0;
        end
    end

    reg [DWIDTH-1:0] temp_sum_acc_result;

    reg [PDEPTH-1:0] rwl;
    always @(posedge clk or negedge reset) begin
        if (reset) begin
            rwl <= 0;
        end else begin
            // rwl <= $random;
            rwl <= 256'hFFFFFFFFFFFFFFFF;
        end
    end

    always @(posedge clk or negedge reset) begin
        if (reset) begin 
            shift_cnt <= 0;
            for (i = 0; i < PWIDTH; i = i+1) begin
                acc_result[i] <= 0;
                adc_out[i] <= 0;
            end
            sum_acc_result <= 0;
            q_reg <= 0;
            mac_out_reg <= 0;

            ready <= 1'b0;
            valid <= 1'b0;
        end else begin
            if (cmd_valid) begin
                ready <= 1'b1;
                if (!p_en) begin // Memory operation
                    if (w_en) begin
                        mem[mem_addr] <= cmd_payload_inputs_0;
                        $display("p_en = %0d, w_en = %0d", p_en, w_en);
                        $display("Write: mem[%d] <= %h", mem_addr, cmd_payload_inputs_0);
                        $display("=====================================================");
                    end else begin
                        q_reg <= mem[mem_addr];
                        $display("p_en = %0d, w_en = %0d", p_en, w_en);
                        $display("Read: mem[%d] -> %h", mem_addr, mem[mem_addr]);
                        $display("=====================================================");
                    end
                    shift_cnt <= 0;
                    for (i = 0; i < PWIDTH; i = i+1) begin
                        acc_result[i] <= 0;
                    end
                end 
                else begin // MAC operation
                    // 
                    $display("p_en = %0d, w_en = %0d", p_en, w_en);
                    
                    for (i = 0; i < PWIDTH; i = i+1) begin
                        acc_result[i] <= (shift_cnt == 0) ? adc_out[i] : acc_result[i] + (adc_out[i] << shift_cnt);
                    end
                    shift_cnt <= shift_cnt + 1;

                    temp_sum_acc_result = 0;
                    for (i = 0; i < PWIDTH; i = i+1) begin
                        temp_sum_acc_result = temp_sum_acc_result + acc_result[i];
                        sum_acc_result <= temp_sum_acc_result;
                    end
                    mac_out_reg <= sum_acc_result;
                end
                valid <= 1'b1;
            end 
            else begin
                ready <= 1'b0;
                valid <= 1'b0;                
            end
        end
    end

    always @(*) begin
        for (i = 0; i < PWIDTH; i = i+1) begin  
            for (j = 0; j < PDEPTH; j = j+1) begin
                if (shift_cnt == 0)     adc_out[i] = 0;
                else                    adc_out[i] = adc_out[i] + ({PWIDTH{mem[PIM_ADDR_BEGIN + j][i]}} & {PWIDTH{rwl[j]}});
            end
        end
    end

    always @(posedge clk or posedge reset) begin
        if(reset) begin
            out <= 32'd0;
        end else begin
            if (p_en) begin
                out <= mac_out_reg;
            end else begin
                if (w_en) begin
                    out <= cmd_payload_inputs_0; 
                    // out <= mem[mem_addr]; 
                end else begin 
                    out <= q_reg;
                end
            end
        end
    end

    assign rsp_payload_outputs_0 = out;

endmodule

simple_pim/model/cfu/sim/EqualTest/fix_test/src/testbench.v
module tb_cfu;

    // Parameters
    parameter PIM_ADDR_BEGIN = 'h000;
    parameter DWIDTH = 32;
    parameter AWIDTH = 10;
    parameter PWIDTH = 32;
    parameter PDEPTH = (1 << AWIDTH);

    // Testbench signals
    reg [PWIDTH-1:0] cmd_payload_inputs_0;
    reg [PWIDTH-1:0] cmd_payload_inputs_1;
    reg [AWIDTH-1:0] cmd_payload_function_id;
    reg clk;
    reg reset;
    reg cmd_valid;
    wire cmd_ready;
    wire rsp_valid;
    reg rsp_ready;
    wire rsp_payload_response_ok;
    wire [DWIDTH-1:0] rsp_payload_outputs_0;

    // Instantiate the CFU module
    cfu #(
        .PIM_ADDR_BEGIN(PIM_ADDR_BEGIN),
        .DWIDTH(DWIDTH),
        .AWIDTH(AWIDTH),
        .PWIDTH(PWIDTH),
        .PDEPTH(PDEPTH)
    ) uut (
        .cmd_payload_inputs_0(cmd_payload_inputs_0),
        .cmd_payload_inputs_1(cmd_payload_inputs_1),
        .cmd_payload_function_id(cmd_payload_function_id),
        .clk(clk),
        .reset(reset),
        .cmd_valid(cmd_valid),
        .cmd_ready(cmd_ready),
        .rsp_valid(rsp_valid),
        .rsp_ready(rsp_ready),
        .rsp_payload_response_ok(rsp_payload_response_ok),
        .rsp_payload_outputs_0(rsp_payload_outputs_0)
    );

    // Clock generation
    always #5 clk = ~clk;

    integer i, j, k, s, mac_index;
    reg [DWIDTH-1:0] write_data [0:255];  // Store the data to write, adjusted size to 256
    reg [DWIDTH-1:0] expected_data [0:255];  // To keep track of what should be written, adjusted size to 256
    reg [DWIDTH-1:0] read_data [0:255];  // To store the read values, adjusted size to 256
    reg [255:0] write_occurred;  // Track if a write occurred at an address, adjusted size to 256
    reg [DWIDTH-1:0] mac_out_array [0:255];
    reg [DWIDTH-1:0] expected_mac_out_array [0:255];
    reg [7:0] addr;  // Address is 8-bit to match address space (0-255)
    reg [9:0] not_match;
    reg [DWIDTH-1:0] expected_mac_out;
    reg [DWIDTH-1:0] mac_out_count;

    reg [DWIDTH-1:0] adc_out [0:PWIDTH-1];
    reg [DWIDTH-1:0] acc_result [0:PWIDTH-1];
    reg [DWIDTH-1:0] mem [0:255];
    reg [31:0] rwl;
    reg [4:0] shift_cnt;
    // reg [4:0] shift_cnt_reg;
    reg test1, test2, test3;
    reg [DWIDTH-1:0] temp_sum_acc_result;
    reg [DWIDTH-1:0] sum_acc_result;

    initial begin
        // Initialize signals
        clk = 0;
        reset = 1;
        cmd_valid = 0;
        rsp_ready = 0;
        cmd_payload_inputs_0 = 0;
        cmd_payload_inputs_1 = 0;
        cmd_payload_function_id = 0;
        not_match = 0;  // Initialize not_match counter
        write_occurred = 0; // Initialize write tracking
        mac_out_count = 0;
        mac_index = 0;  // Initialize mac_out index
        shift_cnt = 0;
        // shift_cnt_reg = 0;
        expected_mac_out = 0;
        sum_acc_result = 0;

        // TEST
        test1 = 0;
        test2 = 1;
        test3 = 1;

        // Apply reset
        #10;
        reset = 0;

        // Initialize data to write, expected data, and read_data
        for (i = 0; i < 256; i = i + 1) begin
            write_data[i] = 32'h0;  // Initialize write data to zero to avoid 'xxxxxxxx'
            expected_data[i] = 32'h0;  // Initialize expected data to zero
            read_data[i] = 32'h0;      // Initialize read value to zero
        end

        $display("=============== TEST START ===============");
        $display("==========================================");

        // Test random write operations for 30 addresses
        // Perform 100 random write operations
        for (s = 0; s < 50; s = s + 1) begin
            $display("TEST [%d]", s);
            addr = $random % 256;  // Choose random address for Write operation
            cmd_payload_function_id = $random % 4;

            // Generate random write data (non-zero)
            write_data[addr] = $random;
            if (write_data[addr] == 0) write_data[addr] = $random | 32'h1; // Ensure non-zero data

            // Handle write operation
            if (cmd_payload_function_id[1:0] == 2'b01) begin
                // Write operation
                cmd_valid = 1;
                cmd_payload_inputs_0 = write_data[addr];  // Data to write
                cmd_payload_inputs_1 = addr;              // Address to write to
                #10;
                cmd_valid = 0;
                #10;

                // Store the written data to expected data for later verification
                expected_data[addr] = write_data[addr];
                write_occurred[addr] = 1; // Mark that a write occurred to this address

                // Display write operation in real-time
                $display("write [%0d] <- %h", addr, write_data[addr]);

                shift_cnt <= 0;
                for (i = 0; i < PWIDTH; i = i+1) begin
                    acc_result[i] <= 0;
                    adc_out[i] <= 0;
                end
            end
            // Handle read operation
            else if (cmd_payload_function_id[1:0] == 2'b00) begin
                cmd_valid = 1;
                cmd_payload_inputs_1 = addr;      // Address to read from
                #10;
                cmd_valid = 0;
                #10;

                // Store the read data
                read_data[addr] = rsp_payload_outputs_0;

                shift_cnt <= 0;
                for (i = 0; i < PWIDTH; i = i+1) begin
                    acc_result[i] <= 0;
                end

                // Display read operation in real-time
                $display("read [%0d] -> %h", addr, rsp_payload_outputs_0);
            end
            // Handle MAC operation (example, display MAC result)
            else begin
                // MAC operation
                cmd_valid = 1;
                cmd_payload_inputs_1 = addr;
                #10;
                cmd_valid = 0;
                #10;

                for (j = 0; j < PWIDTH; j = j + 1) begin
                    if (shift_cnt == 0) adc_out[j] = 0;
                    else begin
                        for (k = 0; k < PDEPTH; k = k + 1) begin
                            adc_out[j] = adc_out[j] + ({32{uut.mem[k][j]}} & {32{uut.rwl[k]}});
                        end
                    end
                end

                for (i = 0; i < PWIDTH; i = i+1) begin
                    acc_result[i] <= (shift_cnt == 0) ? adc_out[i] : acc_result[i] + (adc_out[i] << shift_cnt);
                end

                shift_cnt <= shift_cnt + 1;

                temp_sum_acc_result = 0;
                for (j = 0; j < PWIDTH; j = j + 1) begin
                    temp_sum_acc_result = temp_sum_acc_result + acc_result[j];
                end
                sum_acc_result = temp_sum_acc_result;
                expected_mac_out <= sum_acc_result;
                $display("MAC Result: %h", expected_mac_out); // Print MAC result

                mac_out_array[mac_index] = rsp_payload_outputs_0;
                expected_mac_out_array[mac_index] = expected_mac_out;
                mac_index = mac_index + 1;

                if (mac_index > 1000) begin
                    $display("\nXXX Exceed XXX");
                    $finish;
                end
            end

        end

        $display("\n============= TEST  Evaluate =============");

        // ============================================================================================
        $display("\nTEST 1: Read All");
        $display("address         write                 read");

        // Display the final table of addresses, write and read values
        for (i = 0; i < 256; i = i + 1) begin
            if (write_occurred[i]) begin
                $display("%03d           %h       ->     %h", i, expected_data[i], read_data[i]);
            end 
            else begin
                $display("%03d           00000000              00000000", i);
            end
        end

        if (test1 == 0)         $display("✓ TEST 1 Sucess !");
        else                    $display("x TEST 1 Fail !");

        // ============================================================================================
        $display("\nTEST 2: Read what you wrote");
        $display("address         write                 read");

        for (i = 0; i < 256; i = i + 1) begin
            if (write_occurred[i]) begin
                if (read_data[i] == expected_data[i]) begin
                    $display("%03d           %h       ->     %h", i, expected_data[i], read_data[i]);
                end 
                else if (read_data[i] == 0) begin
                    $display("%03d           %h       ->     %h", i, expected_data[i], read_data[i]);
                end
                else begin
                    $display("%03d           %h              %h  (Mismatch!)", i, expected_data[i], read_data[i]);
                    not_match = not_match + 1;
                    test2 = 0;
                end
            end
        end

        if (test2 == 1)     $display("✓ TEST 2 Sucess !");
        else                $display("x TEST 2 Fail !");
        
        // ============================================================================================
        $display("\nTEST 3: Calculate macout");
        for (i = 0; i < mac_index; i = i + 1) begin
            if (mac_out_array[i] == expected_mac_out_array[i]) begin
                $display("MAC operation %02d: Expected = %h, Actual = %h  (Pass!)", i, expected_mac_out_array[i], mac_out_array[i]);
            end else begin
                $display("MAC operation %02d: Expected = %h, Actual = %h  (Mismatch!)", i, expected_mac_out_array[i], mac_out_array[i]);
                not_match = not_match + 1;
                test3 = 0;
            end
        end

        if (test3 == 1)     $display("✓ TEST 3 Sucess !");
        else                $display("x TEST 3 Fail !");

        // ============================================================================================
        
        if ((test1 == 0) && (test2 == 1) && (test3 == 1)) begin
            $display("\nAll Pass!");
        end 
        else begin
            $display("\nTest completed with %0d mismatches.", not_match);
        end

        $display("==========================================");
        // Finish simulation
        $finish;
    end

    initial begin
        $dumpvars(0, uut);
        $dumpfile("cfu.vcd");
    end

endmodule

simple_pim/model/cfu/sim/EqualTest/fix_test/dump.vcd
$date
	Fri Mar 21 14:08:41 2025
$end
$version
	Icarus Verilog
$end
$timescale
	1s
$end
$scope module tb_cfu $end
$scope module uut $end
$var wire 1 ! clk $end
$var wire 10 " cmd_payload_function_id [9:0] $end
$var wire 32 # cmd_payload_inputs_0 [31:0] $end
$var wire 32 $ cmd_payload_inputs_1 [31:0] $end
$var wire 1 % cmd_ready $end
$var wire 1 & cmd_valid $end
$var wire 1 ' reset $end
$var wire 32 ( rsp_payload_outputs_0 [31:0] $end
$var wire 1 ) rsp_payload_response_ok $end
$var wire 1 * rsp_ready $end
$var wire 1 + rsp_valid $end
$var wire 1 , w_en $end
$var wire 1 - p_en $end
$var wire 8 . mem_addr [7:0] $end
$var reg 32 / mac_out_reg [31:0] $end
$var reg 32 0 out [31:0] $end
$var reg 32 1 q_reg [31:0] $end
$var reg 1 2 ready $end
$var reg 1024 3 rwl [1023:0] $end
$var reg 5 4 shift_cnt [4:0] $end
$var reg 32 5 sum_acc_result [31:0] $end
$var reg 32 6 temp_sum_acc_result [31:0] $end
$var reg 1 7 valid $end
$var integer 32 8 i [31:0] $end
$var integer 32 9 j [31:0] $end
$upscope $end
$upscope $end
$enddefinitions $end
#0
$dumpvars
b10000000000 9
b100000 8
x7
bx 6
bx 5
bx 4
bx 3
x2
bx 1
b0 0
bx /
b0 .
0-
0,
x+
0*
1)
b0 (
1'
0&
x%
b0 $
b0 #
b0 "
0!
$end
#5
b10000000000 9
b0 3
0+
07
0%
02
b0 /
b0 1
b0 5
b0 4
b100000 8
1!
#10
b10000000000 9
1+
17
1%
12
b1111111111111111111111111111111111111111111111111111111111111111 3
b100100 .
1,
b100000 8
0!
b100100 $
b10000100100001001101011000001001 #
1&
b1111111101 "
0'
#15
b10000000000 9
b10000100100001001101011000001001 (
b10000100100001001101011000001001 0
b100000 8
1!
#20
0!
0&
#25
0+
07
0%
02
1!
#30
b1100011 .
0!
b1100011 $
b1000110110111111001100110001101 #
1&
b1 "
#35
b10000000000 9
b1000110110111111001100110001101 (
b1000110110111111001100110001101 0
1+
17
1%
12
b100000 8
1!
#40
0!
0&
#45
0+
07
0%
02
1!
#50
b1100101 .
1-
0,
0!
b1100101 $
1&
b1111111110 "
#55
b10000000000 9
b0 (
b0 0
1+
17
b1 4
1%
12
b0 6
b100000 8
1!
#60
0!
0&
#65
0+
07
0%
02
1!
#70
b1101 .
0!
b1101 $
1&
b10 "
#75
b10000000000 9
1+
17
b10 4
1%
12
b100000 8
1!
#80
0!
0&
#85
0+
07
0%
02
1!
#90
b11101101 .
0-
0!
b11101101 $
1&
b0 "
#95
b10000000000 9
1+
17
b0 4
1%
12
b100000 8
1!
#100
0!
0&
#105
0+
07
0%
02
1!
#110
b11000110 .
1,
0!
b11000110 $
b11010101000100111101001010101010 #
1&
b1111111101 "
#115
b10000000000 9
b11010101000100111101001010101010 (
b11010101000100111101001010101010 0
1+
17
1%
12
b100000 8
1!
#120
0!
0&
#125
0+
07
0%
02
1!
#130
b11100101 .
1-
0!
b11100101 $
1&
b1111111111 "
#135
b10000000000 9
b0 (
b0 0
1+
17
b1 4
1%
12
b100000 8
1!
#140
0!
0&
#145
0+
07
0%
02
1!
#150
b10001111 .
0,
0!
b10001111 $
1&
b10 "
#155
b10000000000 9
1+
17
b10 4
1%
12
b100000 8
1!
#160
0!
0&
#165
0+
07
0%
02
1!
#170
b11101000 .
0-
1,
0!
b11101000 $
b101110010110000100100101011100 #
1&
b1111111101 "
#175
b10000000000 9
b101110010110000100100101011100 (
b101110010110000100100101011100 0
1+
17
b0 4
1%
12
b100000 8
1!
#180
0!
0&
#185
0+
07
0%
02
1!
#190
b10111101 .
0!
b10111101 $
b10110010101001110010011001100101 #
1&
#195
b10000000000 9
b10110010101001110010011001100101 (
b10110010101001110010011001100101 0
1+
17
1%
12
b100000 8
1!
#200
0!
0&
#205
0+
07
0%
02
1!
#210
b1100011 .
1-
0,
0!
b1100011 $
1&
b10 "
#215
b10000000000 9
b0 (
b0 0
1+
17
b1 4
1%
12
b100000 8
1!
#220
0!
0&
#225
0+
07
0%
02
1!
#230
b100000 .
0!
b100000 $
1&
#235
b10000000000 9
1+
17
b10 4
1%
12
b100000 8
1!
#240
0!
0&
#245
0+
07
0%
02
1!
#250
b10010110 .
1,
0!
b10010110 $
1&
b1111111111 "
#255
b10000000000 9
1+
17
b11111111111111111111111111101010 5
b11 4
1%
12
b11111111111111111111111111101010 6
b100000 8
1!
#260
0!
0&
#265
0+
07
0%
02
1!
#270
b1010011 .
0!
b1010011 $
1&
b11 "
#275
b10000000000 9
1+
17
b11111111111111111111111111101010 /
b11111111111111111111111110010010 5
b100 4
1%
12
b11111111111111111111111110010010 6
b100000 8
1!
#280
0!
0&
#285
b11111111111111111111111111101010 (
b11111111111111111111111111101010 0
0+
07
0%
02
1!
#290
b10 .
0,
0!
b10 $
1&
b1111111110 "
#295
b10000000000 9
1+
17
b11111111111111111111111110010010 /
b11111111111111111111111010001010 5
b101 4
1%
12
b11111111111111111111111010001010 6
b100000 8
1!
#300
0!
0&
#305
b11111111111111111111111110010010 (
b11111111111111111111111110010010 0
0+
07
0%
02
1!
#310
b11001111 .
1,
0!
b11001111 $
1&
b11 "
#315
b10000000000 9
1+
17
b11111111111111111111111010001010 /
b11111111111111111111101111001010 5
b110 4
1%
12
b11111111111111111111101111001010 6
b100000 8
1!
#320
0!
0&
#325
b11111111111111111111111010001010 (
b11111111111111111111111010001010 0
0+
07
0%
02
1!
#330
b11001010 .
0-
0,
0!
b11001010 $
1&
b0 "
#335
b10000000000 9
b0 (
b0 0
1+
17
b0 4
1%
12
b100000 8
1!
#340
0!
0&
#345
0+
07
0%
02
1!
#350
b10001010 .
1,
0!
b10001010 $
b11101100010010110011010011011000 #
1&
b1 "
#355
b10000000000 9
b11101100010010110011010011011000 (
b11101100010010110011010011011000 0
1+
17
1%
12
b100000 8
1!
#360
0!
0&
#365
0+
07
0%
02
1!
#370
b1111000 .
0!
b1111000 $
b1110101110001010000110111101011 #
1&
b1111111101 "
#375
b10000000000 9
b1110101110001010000110111101011 (
b1110101110001010000110111101011 0
1+
17
1%
12
b100000 8
1!
#380
0!
0&
#385
0+
07
0%
02
1!
#390
b10110110 .
1-
0,
0!
b10110110 $
1&
b10 "
#395
b10000000000 9
b11111111111111111111111010001010 (
b11111111111111111111111010001010 0
1+
17
b11111111111111111111101111001010 /
b0 5
b1 4
1%
12
b0 6
b100000 8
1!
#400
0!
0&
#405
b11111111111111111111101111001010 (
b11111111111111111111101111001010 0
0+
07
0%
02
1!
#410
b10111100 .
0!
b10111100 $
1&
#415
b10000000000 9
1+
17
b0 /
b10 4
1%
12
b100000 8
1!
#420
0!
0&
#425
b0 (
b0 0
0+
07
0%
02
1!
#430
b1110001 .
0-
1,
0!
b1110001 $
b100111111100100101010101001111 #
1&
b1 "
#435
b10000000000 9
b100111111100100101010101001111 (
b100111111100100101010101001111 0
1+
17
b0 4
1%
12
b100000 8
1!
#440
0!
0&
#445
0+
07
0%
02
1!
#450
b111011 .
1-
0,
0!
b111011 $
1&
b10 "
#455
b10000000000 9
b0 (
b0 0
1+
17
b1 4
1%
12
b100000 8
1!
#460
0!
0&
#465
0+
07
0%
02
1!
#470
b10101 .
0-
1,
0!
b10101 $
b1101100100111000100101111011001 #
1&
b1 "
#475
b10000000000 9
b1101100100111000100101111011001 (
b1101100100111000100101111011001 0
1+
17
b0 4
1%
12
b100000 8
1!
#480
0!
0&
#485
0+
07
0%
02
1!
#490
b1100010 .
0,
0!
b1100010 $
1&
b0 "
#495
b0 (
b0 0
1+
17
1%
12
b100000 8
1!
#500
0!
0&
#505
0+
07
0%
02
1!
#510
b10001111 .
0!
b10001111 $
1&
#515
1+
17
1%
12
b100000 8
1!
#520
0!
0&
#525
0+
07
0%
02
1!
#530
b10011111 .
0!
b10011111 $
1&
#535
1+
17
1%
12
b100000 8
1!
#540
0!
0&
#545
0+
07
0%
02
1!
#550
b10001001 .
1,
0!
b10001001 $
b11101000001000110011111011010000 #
1&
b1111111101 "
#555
b10000000000 9
b11101000001000110011111011010000 (
b11101000001000110011111011010000 0
1+
17
1%
12
b100000 8
1!
#560
0!
0&
#565
0+
07
0%
02
1!
#570
b11010111 .
0!
b11010111 $
b1001011001000010010111110010110 #
1&
#575
b10000000000 9
b1001011001000010010111110010110 (
b1001011001000010010111110010110 0
1+
17
1%
12
b100000 8
1!
#580
0!
0&
#585
0+
07
0%
02
1!
#590
b1100 .
1-
0,
0!
b1100 $
1&
b1111111110 "
#595
b10000000000 9
b0 (
b0 0
1+
17
b1 4
1%
12
b100000 8
1!
#600
0!
0&
#605
0+
07
0%
02
1!
#610
b1110111 .
0-
1,
0!
b1110111 $
b1001000011001101101100010010 #
1&
b1 "
#615
b10000000000 9
b1001000011001101101100010010 (
b1001000011001101101100010010 0
1+
17
b0 4
1%
12
b100000 8
1!
#620
0!
0&
#625
0+
07
0%
02
1!
#630
b1111110 .
0!
b1111110 $
b11100110110011110011100111001 #
1&
#635
b10000000000 9
b11100110110011110011100111001 (
b11100110110011110011100111001 0
1+
17
1%
12
b100000 8
1!
#640
0!
0&
#645
0+
07
0%
02
1!
#650
b11111 .
1-
0!
b11111 $
1&
b1111111111 "
#655
b10000000000 9
b0 (
b0 0
1+
17
b1 4
1%
12
b100000 8
1!
#660
0!
0&
#665
0+
07
0%
02
1!
#670
b1111000 .
0!
b1111000 $
1&
b11 "
#675
b10000000000 9
1+
17
b10 4
1%
12
b100000 8
1!
#680
0!
0&
#685
0+
07
0%
02
1!
#690
b111111 .
0,
0!
b111111 $
1&
b10 "
#695
b10000000000 9
1+
17
b11111111111111111111111111001000 5
b11 4
1%
12
b11111111111111111111111111001000 6
b100000 8
1!
#700
0!
0&
#705
0+
07
0%
02
1!
#710
b10000110 .
0!
b10000110 $
1&
b1111111110 "
#715
b10000000000 9
1+
17
b11111111111111111111111111001000 /
b11111111111111111111111011101000 5
b100 4
1%
12
b11111111111111111111111011101000 6
b100000 8
1!
#720
0!
0&
#725
b11111111111111111111111111001000 (
b11111111111111111111111111001000 0
0+
07
0%
02
1!
#730
b11111010 .
0!
b11111010 $
1&
#735
b10000000000 9
1+
17
b11111111111111111111111011101000 /
b11111111111111111111110001001000 5
b101 4
1%
12
b11111111111111111111110001001000 6
b100000 8
1!
#740
0!
0&
#745
b11111111111111111111111011101000 (
b11111111111111111111111011101000 0
0+
07
0%
02
1!
#750
b10100011 .
1,
0!
b10100011 $
1&
b1111111111 "
#755
b10000000000 9
1+
17
b11111111111111111111110001001000 /
b11111111111111111111010101001000 5
b110 4
1%
12
b11111111111111111111010101001000 6
b100000 8
1!
#760
0!
0&
#765
b11111111111111111111110001001000 (
b11111111111111111111110001001000 0
0+
07
0%
02
1!
#770
b1011111 .
0-
0,
0!
b1011111 $
1&
b0 "
#775
b10000000000 9
b0 (
b0 0
1+
17
b0 4
1%
12
b100000 8
1!
#780
0!
0&
#785
0+
07
0%
02
1!
#790
b11001011 .
1-
0!
b11001011 $
1&
b1111111110 "
#795
b10000000000 9
b11111111111111111111110001001000 (
b11111111111111111111110001001000 0
1+
17
b11111111111111111111010101001000 /
b0 5
b1 4
1%
12
b0 6
b100000 8
1!
#800
0!
0&
#805
b11111111111111111111010101001000 (
b11111111111111111111010101001000 0
0+
07
0%
02
1!
#810
b101001 .
0-
1,
0!
b101001 $
b11101101010100110110110011011010 #
1&
b1111111101 "
#815
b10000000000 9
b11101101010100110110110011011010 (
b11101101010100110110110011011010 0
1+
17
b0 4
1%
12
b100000 8
1!
#820
0!
0&
#825
0+
07
0%
02
1!
#830
b1100101 .
0!
b1100101 $
b11101111101111101001010011011111 #
1&
#835
b10000000000 9
b11101111101111101001010011011111 (
b11101111101111101001010011011111 0
1+
17
1%
12
b100000 8
1!
#840
0!
0&
#845
0+
07
0%
02
1!
#850
b1111001 .
0,
0!
b1111001 $
1&
b0 "
#855
b0 (
b0 0
1+
17
1%
12
b100000 8
1!
#860
0!
0&
#865
0+
07
0%
02
1!
#870
b101010 .
1-
1,
0!
b101010 $
1&
b11 "
#875
b10000000000 9
b11111111111111111111010101001000 (
b11111111111111111111010101001000 0
1+
17
b0 /
b1 4
1%
12
b100000 8
1!
#880
0!
0&
#885
b0 (
b0 0
0+
07
0%
02
1!
#890
b11011100 .
0,
0!
b11011100 $
1&
b1111111110 "
#895
b10000000000 9
1+
17
b10 4
1%
12
b100000 8
1!
#900
0!
0&
#905
0+
07
0%
02
1!
#910
b11000011 .
0!
b11000011 $
1&
b10 "
#915
b10000000000 9
1+
17
b11111111111111111111111110100010 5
b11 4
1%
12
b11111111111111111111111110100010 6
b100000 8
1!
#920
0!
0&
#925
0+
07
0%
02
1!
#930
b1100111 .
0!
b1100111 $
1&
b1111111110 "
#935
b10000000000 9
1+
17
b11111111111111111111111110100010 /
b11111111111111111111111000101010 5
b100 4
1%
12
b11111111111111111111111000101010 6
b100000 8
1!
#940
0!
0&
#945
b11111111111111111111111110100010 (
b11111111111111111111111110100010 0
0+
07
0%
02
1!
#950
b111000 .
0-
1,
0!
b111000 $
b11011100001010111100010010111000 #
1&
b1 "
#955
b10000000000 9
b11011100001010111100010010111000 (
b11011100001010111100010010111000 0
1+
17
b0 4
1%
12
b100000 8
1!
#960
0!
0&
#965
0+
07
0%
02
1!
#970
b10010100 .
1-
0!
b10010100 $
1&
b11 "
#975
b10000000000 9
b11111111111111111111111110100010 (
b11111111111111111111111110100010 0
1+
17
b11111111111111111111111000101010 /
b0 5
b1 4
1%
12
b0 6
b100000 8
1!
#980
0!
0&
#985
b11111111111111111111111000101010 (
b11111111111111111111111000101010 0
0+
07
0%
02
1!
#990
b1011001 .
0!
b1011001 $
1&
#995
b10000000000 9
1+
17
b0 /
b10 4
1%
12
b100000 8
1!
#1000
0!
0&
#1005
b0 (
b0 0
0+
07
0%
02
1!
